Workbook

Sheet RESTAURANTESDESCUENTOS 2026
A1: 0 | B1: DESCUENTO | C1: RAZON SOCIAL | D1: ACTIVO | E1: PRODUCTO | F1: DOMICILIO | G1: OBSERVACIONES | H1: MARCACION | I1: CRÉDITO | J1: DIRECCION
A2: HIJO DE TIGRE | B2: 0.25 | C2: BODEGA LEOPARDO | D2: ACTIVO | E2: GRANDE ORIGINAL - R | F2: LUNES Y JUEVES N/A OTRO DÍA $10.000 | H2: X10 | I2: 15 DÍAS | J2: COMPLEX LOS BALSOS Cra. 25 #12 Sur-59, El Poblado
A3: ENTRECOTE BY CATA INTERPLAZA | B3: 0.25 | C3: CATALINA FERNANDEZ SAS | D3: ACTIVO | E3: GRANDE ORIGINAL - R | F3: 10000 | H3: X10 | I3: 8 DÍAS | J3: INTERPLAZA Cra. 30 #10C-228, El Poblado
A4: ENTRECOTE BY CATA INDIANA | B4: 0.25 | C4: CATALINA FERNANDEZ SAS | D4: ACTIVO | E4: GRANDE ORIGINAL - R | F4: 15000 | H4: X10 | I4: 8 DÍAS | J4: INDIANA MALL #Local 121, Las Palmas
A5: ENTRECOTE BY CATA RETIRO | B5: 0.25 | C5: CATALINA FERNANDEZ SAS | D5: ACTIVO | E5: GRANDE ORIGINAL - R | F5: 25000 | H5: X10 | I5: 8 DÍAS | J5: Cra. 20 #19-30, Retiro, Antioquia
A6: LA ABUELA NITA | B6: 0.25 | C6: ENSORE SAS | D6: ACTIVO | E6: GRANDE ORIGINAL - R | F6: N/A | H6: X12 | I6: 8 DÍAS | J6: Mall Punto de Encuentro
A7: ERNESTO SALON COMEDOR | B7: 0.25 | C7: SIMON RESTREPO CALLE | D7: ACTIVO | E7: GRANDE ORIGINAL - R | F7: 25000 | H7: X10 | I7: 8 DÍAS | J7: Sector el altico, Cra. 20 #23-39, Retiro, Antioquia
A8: AMMAZZA LAURELES | B8: 0.25 | C8: AMMAZZA LAURELES SAS | D8: NO | E8: MEDIANA ORIGINAL - R | F8: N/A | H8: X10 | I8: 8 DÍAS | J8: Cra. 76 #73b - 39, Laureles - Estadio
A9: AMMAZZA INDIANA | B9: 0.25 | C9: AMMAZZA INDIANA SAS | D9: NO | E9: MEDIANA ORIGINAL - R | F9: N/A | H9: X10 | I9: 8 DÍAS | J9: INDIANA MALL #Local 121, Las Palmas
A10: AMMAZZA AMSTERDAM | B10: 0.25 | C10: AMMAZZA AMSTERDAM SAS | D10: NO | E10: MEDIANA ORIGINAL - R | F10: N/A | H10: X10 | I10: 8 DÍAS | J10: AMSTERDAM PLAZA Cra. 25 #4-165, El Poblado
A11: BARBARO POBLADO | B11: 0.25 | C11: BARBARO POBLADO SAS | D11: NO | E11: MEDIANA ORIGINAL - R | F11: N/A | H11: X10 | I11: 8 DÍAS | J11: Cra. 37 #10a-23, El Poblado
A12: BARBARO LAURELES | B12: 0.25 | C12: BARBARO LAURELES SAS | D12: NO | E12: MEDIANA ORIGINAL - R | F12: N/A | H12: X10 | I12: 8 DÍAS | J12: Cra. 76 #73b-39, Laureles - Estadio
A13: BARBARO RIONEGRO | B13: 0.25 | C13: BARBARO RIONEGRO SAS | D13: NO | E13: MEDIANA ORIGINAL - R | F13: N/A | H13: X10 | I13: 8 DÍAS | J13: Rionegro, Antioquia
A14: BARBARO VIVA ENVIGADO | B14: 0.25 | C14: BARBARO VIVA ENVIGADO SAS | D14: NO | E14: MEDIANA ORIGINAL - R | F14: N/A | H14: X10 | I14: 8 DÍAS | J14: Cra. 48 #32B Sur-139
A15: CASA DE NADIE | B15: 0.25 | C15: INVERSIONES ENTRE PINOS SAS | D15: ACTIVO | E15: GRANDE ORIGINAL - R | F15: 10000 | G15: Tambien piden bites originales y les quedan en 4.000 | H15: X12 | I15: 8 DÍAS | J15: Loma los balsos, Casaloma, Medellín
A16: GRILL STATION POBLADO | B16: 0.25 | C16: FAIPA FRANQUICIAS SAS | D16: ACTIVO | E16: GRANDE ORIGINAL - R | F16: N/A | G16: SE FACTURA AREQUIPE-200 CANTIDAD- $110 VALOR UNITARIO | H16: X10 | I16: 8 DÍAS | J16: PROVENZA Cra. 34 #7-90, El Poblado
A17: GRILL STATION LAURELES | B17: 0.25 | C17: FAIPA FRANQUICIAS SAS | D17: ACTIVO | E17: GRANDE ORIGINAL - R | F17: N/A | G17: SE FACTURA AREQUIPE-200 CANTIDAD- $110 VALOR UNITARIO | H17: X10 | I17: 8 DÍAS | J17: Cq. 76 #73B-17, Laureles - Estadio
A18: GRILL STATION COLORES | B18: 0.25 | C18: FAIPA FRANQUICIAS SAS | D18: ACTIVO | E18: GRANDE ORIGINAL - R | F18: N/A | G18: SE FACTURA AREQUIPE-200 CANTIDAD- $110 VALOR UNITARIO | H18: X10 | I18: 8 DÍAS | J18: MALL LOS COLORES Cl. 53 #72-44, Laureles - Estadio, Medellín
A19: GRILL STATION LLANOGRANDE | B19: 0.25 | C19: FAIPA FRANQUICIAS SAS | D19: ACTIVO | E19: GRANDE ORIGINAL - R | F19: N/A | G19: SE FACTURA AREQUIPE-200 CANTIDAD- $110 VALOR UNITARIO | H19: X10 | I19: 8 DÍAS | J19: Mall Jardines de Llanogrande
A20: GRILL STATION SAN LUCAS | B20: 0.25 | C20: FAIPA FRANQUICIAS SAS | D20: ACTIVO | E20: GRANDE ORIGINAL - R | F20: N/A | G20: SE FACTURA AREQUIPE-200 CANTIDAD- $110 VALOR UNITARIO | H20: X10 | I20: 8 DÍAS | J20: San Lucas Plaza, Cl. 20 Sur #27-55 Of. 9980
A21: GRILL STATION ENVIGADO | B21: 0.25 | C21: FAIPA FRANQUICIAS SAS | D21: ACTIVO | E21: GRANDE ORIGINAL - R | F21: N/A | G21: SE FACTURA AREQUIPE-200 CANTIDAD- $110 VALOR UNITARIO | H21: X10 | I21: 8 DÍAS | J21: Calle 36d sur # 27a-105, LOCAL 350
A22: AZUL SELVA | B22: 0.25 | C22: GRUPO AS SAS | D22: ACTIVO | E22: GRANDE ORIGINAL - R | F22: N/A | G22: PAGA TODOS LOS 30 DEL MES | H22: X12 | I22: 30 DÍAS | J22: VIA PRIMAVERA Cra. 37 #8a-60, El Poblado
A23: EL CAFE CHALET | B23: 0.25 | C23: HAROLD RAMOS VARGAS | D23: ACTIVO | E23: GRANDE ORIGINAL - R | F23: N/A | H23: X12 | I23: 8 DÍAS
A24: MIENTRAS TIN TO | B24: 0.25 | C24: JOHAN ALEJANDRO RAMIREZ GIRALDO | D24: ACTIVO | E24: GRANDE ORIGINAL - R | F24: N/A | H24: X10 | I24: 8 DÍAS
A25: SANTIAGO FARLEY COCINA | B25: 0.25 | C25: SANTIAGO FARLEY CASTAÑO | D25: ACTIVO | E25: VARIEDAD | F25: DEPENDE DEL LUGAR (ANDRES NOS DICE) | I25: 8 DÍAS
A26: SHIBUYA | B26: 0.25 | C26: TORRES SANTIAGO OCAMPO | D26: ACTIVO | E26: MEDIANA ORIGINAL - R | F26: N/A | H26: X10 | I26: 8 DÍAS | J26: INDIANA MALL #Local 121, Las Palmas
A27: LA FRAGUA | B27: 0.25 | C27: CON CARITA DE NADA SAS | D27: ACTIVO | E27: MEDIANA ORIGINAL - R | F27: 10000 | G27: TAMBIEN PIDE GRANDE X12 | H27: X10 | I27: 8 DÍAS | J27: Escuela De Equitacion EQUUS Zuniga Parte Alta
A28: MERO | B28: 0.3 | C28: MERO SAS 901.444.356-0 | D28: ACTIVO | E28: GRANDE ORIGINAL - R | F28: 5000 | G28: SE FACTURA FRUTOS ROJOS-150 CANTIDAD- $110 VALOR UNITARIO | H28: X10 | I28: 8 DÍAS | J28: MALL ZONA 2 Cra. 32 #2 Sur 47, El Poblado
A29: ENSO | B29: 0.3 | C29: CORANTE SAS | D29: ACTIVO | E29: GRANDE ORIGINAL - R | F29: 5000 | H29: X10 | I29: 8 DÍAS | J29: Carrera 36 #8a39 Poblado
A30: GENERAL CAFE | B30: 0.3 | C30: GENERAL CAFE Y BAR SAS | D30: ACTIVO | E30: GRANDE ORIGINAL - R | F30: 5000 | G30: Horario de recepcion 7am-6pm | H30: X10 | I30: 8 DÍAS | J30: Cl. 13 #43D-84 Local 101, 102, El Poblado
A31: CASA FLORA | B31: 0.3 | C31: BOHEMIAN FLOWERS S.A.S | D31: ACTIVO | E31: GRANDE ORIGINAL - R | F31: 10000 | H31: X12 | I31: 15 DÍAS | J31: Cruce EL TABLAZO, via Rionegro
A32: AMBIENTE LIVING | B32: 0.3525 | C32: LIVING RESTAURANTES | D32: ACTIVO | E32: GRANDE ORIGINAL - R | F32: 8000 | H32: X10 | I32: 8 DÍAS | J32: TESORO CENTRO COMERCIAL
A33: VELEZ CAFE EL TESORO | C33: CAFE ARTISAN SAS | D33: ACTIVO | E33: MINI ORIGINAL - VELEZ CAFE | G33: SOLO SE DESPACHA MIERCOLES Y VIERNES Horario permitido entregas: 9:00am – 11:00 am | I33: 30 DÍAS | J33: TESORO CENTRO COMERCIAL PISO 2
A34: VELEZ CAFE EL TESORO | C34: CAFE ARTISAN SAS | D34: ACTIVO | E34: MINI PISTACHO - VELEZ CAFE | F34: N/A | G34: SOLO SE DESPACHA MIERCOLES Y VIERNES Horario permitido entregas: 9:00am – 11:00 am | I34: 30 DÍAS
A35: VELEZ CAFE EL TESORO | C35: CAFE ARTISAN SAS | D35: ACTIVO | E35: MINI MILO - VELEZ CAFE | G35: SOLO SE DESPACHA MIERCOLES Y VIERNES Horario permitido entregas: 9:00am – 11:00 am | I35: 30 DÍAS
A36: VELEZ CAFE SANTAFE | C36: CAFE ARTISAN SAS | D36: ACTIVO | E36: MINI ORIGINAL - VELEZ CAFE | G36: SOLO SE DESPACHA MIERCOLES Y VIERNES Horario permitido entregas: 8:00am – 11:00 am | I36: 30 DÍAS | J36: CC SANTAFE PISO 2
A37: VELEZ CAFE SANTAFE | C37: CAFE ARTISAN SAS | D37: ACTIVO | E37: MINI PISTACHO - VELEZ CAFE | F37: N/A | G37: SOLO SE DESPACHA MIERCOLES Y VIERNES Horario permitido entregas: 8:00am – 11:00 am | I37: 30 DÍAS
A38: VELEZ CAFE SANTAFE | C38: CAFE ARTISAN SAS | D38: ACTIVO | E38: MINI MILO - VELEZ CAFE | G38: SOLO SE DESPACHA MIERCOLES Y VIERNES Horario permitido entregas: 8:00am – 11:00 am | I38: 30 DÍAS
A39: VELEZ CAFE CALI | C39: CAFE ARTISAN SAS | D39: ACTIVO | E39: MINI ORIGINAL - VELEZ CAFE | G39: RECIBEN DE 9AM A 11 AM TOCA ENVIAR CON TRANSPORTADORA HACIA CALI Nevera M: caben 108 mini tartas Nevera XM: caben 204 mini tartas | I39: 30 DÍAS | J39: Calle 3 # 52 - 253, Cuarto de Legua #52-253, Cali - Mallplaza
A40: VELEZ CAFE CALI | C40: CAFE ARTISAN SAS | D40: ACTIVO | E40: MINI PISTACHO - VELEZ CAFE | G40: RECIBEN DE 9AM A 11 AM TOCA ENVIAR CON TRANSPORTADORA HACIA CALI Nevera M: caben 108 mini tartas Nevera XM: caben 204 mini tartas | I40: 30 DÍAS
A41: VELEZ CAFE CALI | C41: CAFE ARTISAN SAS | D41: ACTIVO | E41: MINI MILO - VELEZ CAFE | F41: 298000 | G41: RECIBEN DE 9AM A 11 AM TOCA ENVIAR CON TRANSPORTADORA HACIA CALI Nevera M: caben 108 mini tartas Nevera XM: caben 204 mini tartas | I41: 30 DÍAS
A42: VELEZ CAFE EDIFICIO | C42: CAFE ARTISAN SAS | D42: ACTIVO | E42: BITE X16 ORIGINAL VELEZ CAFE | I42: 30 DÍAS | J42: Calle 29 # 52-115 Ed. Cueros Velez (Guayabal)
A43: VELEZ CAFE EDIFICIO | C43: CAFE ARTISAN SAS | D43: ACTIVO | E43: BITE X16 MILO VELEZ CAFE | I43: 30 DÍAS
A44: VELEZ CAFE EDIFICIO | C44: CAFE ARTISAN SAS | D44: ACTIVO | E44: BITE X16 PISTACHO VELEZ CAFE | I44: 30 DÍAS
A45: LONDRES COCINA BAR | B45: 0.3 | C45: MELANY GUTIERREZ ORTIZ | D45: ACTIVO | E45: GRANDE ORIGINAL - R | F45: 10000 | H45: X10 | I45: 8 DÍAS | J45: "CAMPO VALDEZ Cl. 77 #48a-05, Aranjuez
A46: BURDO | B46: 0.3 | C46: BURDO PROVENZA SAS | D46: ACTIVO | E46: GRANDE ORIGINAL - R | F46: 5000 | H46: X10 | I46: 8 DÍAS | J46: Hotel Click Clack, Cl. 10b #37 29, El Poblado, Medellín
A47: EGEO | B47: 0.3 | C47: EGEO INVERSIONES SAS | D47: ACTIVO | E47: MEDIANA PISTACHO - R | F47: 5000 | H47: X10 | I47: 8 DÍAS
A51: LE PALITO | D51: PENDIENTE
A52: BONHOMIA | D52: PENDIENTE
A53: HASTA LA PIZZA | D53: PENDIENTE
A54: BASTARDO | D54: PENDIENTE
A56: FELIPE GOMEZ | B56: 0.25 | C56: 1001013801
A57: VERONICA MELO | B57: 0.25 | C57: 1000547706
A58: ANDREA OCHOA | B58: 0.25
A59: MANUELA SALDARRIAGA | B59: 0.25
A60: CATALINA VELEZ | B60: 0.25
A61: PALOMA URREA | B61: 0.25
A62: ELISA MARTINEZ BERNAL | B62: 0.25
A63: ALEJANDRA CASTAÑO | B63: 0.25
A64: MARIA JOSE PELAEZ | B64: 0.25
A65: DIANA ARREDONDO | B65: 0.25 | C65: 42885057
A66: ALBERTO GOMEZ | B66: 0.25
A67: SUSANA GOMEZ | B67: 0.25 | C67: 1037653521
A68: SOFIA GOMEZ | B68: 0.25 | C68: 1017272942
A69: VICENTE ARISTIZABAL | B69: 0.25
A70: JUAN CAMILO MARTINEZ | B70: 0.25
A71: TOMAS ARANGO | B71: 0.25
A72: LUCY PELAEZ | B72: 0.25
A73: MARIANA GOMEZ | B73: 0.25
A74: JUANITA GOMEZ | B74: 0.25
A75: SERGIO GOMEZ | B75: 0.25 | C75: 71577385
A76: DIANA MARCELA JARAMILLO | B76: 0.3 | C76: 1045112518
A77: ANDRES TARTELLE | B77: 0.3
A78: ANA TARTELLE | B78: 0.3
A79: CINDY TARTELLE | B79: 0.3 | C79: 1128326794
A80: DANIELA TARTELLE | B80: 0.3 | C80: 1001420512
A81: ANDREA GOMEZ | B81: 1 | C81: 1001367660
A82: JHON DOMICILIARIO | B82: 0.3 | C82: 18595631
A83: LUCIA LOPEZ | B83: 0.25 | C83: 32076494

Sheet INVENTARIO DIARIO PT
A1: FECHA | B1: CANTIDAD | C1: PRODUCTO | D1: COMENTARIOS | E1: REVISADO
A2: 46062 | B2: 3 | C2: PORCION OG | E2: DANIELA
A3: 46062 | B3: 16 | C3: MINI OG | E3: DANIELA
A4: 46062 | B4: 16 | C4: MEDIANA OG | E4: DANIELA
A5: 46062 | B5: 15 | C5: GRANDE OG | E5: DANIELA
A6: 46062 | B6: 6 | C6: MINI ORIGINAL X COOKIE WORLD | E6: DANIELA
A7: 46062 | B7: 5 | C7: MEDIANA ORIGINAL X COOKIE WORLD | E7: DANIELA
A8: 46062 | B8: 1 | C8: MEDIANA PISTACHO | E8: DANIELA
A9: 46062 | B9: 1 | C9: BITES X4 OG | E9: DANIELA
A10: 46062 | B10: 21 | C10: MINI ORIGINAL VELEZ CAFE | E10: DANIELA
A11: 46062 | B11: 9 | C11: MINI PISTACHO VELEZ CAFE | E11: DANIELA
A12: 46062 | B12: 6 | C12: MINI MILO CAFE VELEZ CAFE | E12: DANIELA
A13: 46063 | B13: 10 | C13: PORCION OG | E13: DANIELA
... A229: 46090 | B229: 10 | C229: MINI MILO CAFE VELEZ CAFE | E229: DANIELA
A230: 46091 | B230: 12 | C230: GRANDE OG | D230: 2 Grandes factura doble la abuela nita | E230: DANIELA
A231: 46091 | B231: 20 | C231: MEDIANA OG | E231: DANIELA
A232: 46091 | B232: 8 | C232: MINI OG | E232: DANIELA
A233: 46091 | B233: 6 | C233: MINI LOTUS | E233: DANIELA
A234: 46091 | B234: 3 | C234: MINI VAINILLA | E234: DANIELA
A235: 46091 | B235: 1 | C235: MINI MILO | E235: DANIELA
A236: 46091 | B236: 5 | C236: BITES X4 OG | E236: DANIELA
A237: 46091 | B237: 3 | C237: PORCION OG | E237: DANIELA
A238: 46091 | B238: 1 | C238: MINI PISTACHO | E238: DANIELA
A239: 46092 | B239: 19 | C239: GRANDE OG | E239: DANIELA
A240: 46092 | B240: 15 | C240: MEDIANA OG | E240: DANIELA
A241: 46092 | B241: 17 | C241: MINI OG | E241: DANIELA
A242: 46092 | B242: 4 | C242: MINI PISTACHO | E242: DANIELA
... A355: 46105 | B355: 10 | C355: MINI OG | E355: DANIELA
A356: 46105 | B356: 7 | C356: PORCION OG | D356: 2 MAS, PEDIDO CANCELADO DE RAPPI | E356: DANIELA
A357: 46105 | B357: 1 | C357: GRANDE VAINILLA | E357: DANIELA
A358: 46105 | B358: 1 | C358: MEDIANA PISTACHO | E358: DANIELA
A359: 46105 | B359: 2 | C359: MEDIANA LOTUS | E359: DANIELA
A360: 46105 | B360: 2 | C360: MEDIANA VAINILLA | E360: DANIELA
A361: 46105 | B361: 4 | C361: MINI LOTUS | E361: DANIELA
A362: 46105 | B362: 1 | C362: MINI VAINILLA | E362: DANIELA
A363: 46105 | B363: 4 | C363: MINI PISTACHO | E363: DANIELA
A364: 46105 | B364: 7 | C364: BITES X4 OG | E364: DANIELA
A365: 46106 | B365: 29 | C365: GRANDE OG | E365: DANIELA
A366: 46106 | B366: 25 | C366: MEDIANA OG | E366: DANIELA
A367: 46106 | B367: 19 | C367: MINI OG | E367: DANIELA
A368: 46106 | B368: 9 | C368: PORCION OG | E368: DANIELA
... A449: 46116 | B449: 12 | C449: GRANDE OG | E449: DANIELA
A450: 46116 | B450: 23 | C450: MEDIANA OG | D450: UNA DE MAS | E450: DANIELA
A451: 46116 | B451: 16 | C451: MINI OG | E451: DANIELA
A452: 46116 | B452: 12 | C452: PORCION OG | E452: DANIELA
A453: 46116 | B453: 1 | C453: GRANDE VAINILLA | E453: DANIELA
A454: 46116 | B454: 1 | C454: MEDIANA PISTACHO | E454: DANIELA
A455: 46116 | B455: 3 | C455: MEDIANA LOTUS | E455: DANIELA
A456: 46116 | B456: 3 | C456: MINI LOTUS | E456: DANIELA
A457: 46116 | B457: 5 | C457: MINI PISTACHO | E457: DANIELA
A458: 46116 | B458: 2 | C458: BITES X4 OG | E458: DANIELA
A459: 46118 | B459: 13 | C459: GRANDE OG | E459: DANIELA
A460: 46118 | B460: 23 | C460: MEDIANA OG | E460: DANIELA
A461: 46118 | B461: 13 | C461: MINI OG | E461: DANIELA
A462: 46118 | B462: 10 | C462: PORCION OG | E462: DANIELA
... A470: 46119 | B470: 13 | C470: MINI OG | E470: DANIELA
A471: 46119 | B471: 6 | C471: PORCION OG | D471: -3 PORCIONES | E471: DANIELA
A472: 46119 | B472: 2 | C472: MINI LOTUS | E472: DANIELA
A473: 46119 | B473: 4 | C473: MINI PISTACHO | E473: DANIELA
A474: 46119 | B474: 1 | C474: CUCHAREABLE LOTUS | E474: DANIELA
A475: 46119 | B475: 3 | C475: CUCHAREABLE MILO | E475: DANIELA
A476: 46119 | B476: 2 | C476: CUCHAREABLE AREQUIPE | E476: DANIELA
A477: 46120 | B477: 23 | C477: GRANDE OG | E477: DANIELA
A478: 46120 | B478: 15 | C478: MEDIANA OG | E478: DANIELA
A479: 46120 | B479: 7 | C479: MINI OG | E479: DANIELA
A480: 46120 | B480: 1 | C480: PORCION OG | E480: DANIELA
A481: 46120 | B481: 2 | C481: MINI LOTUS | E481: DANIELA
A482: 46120 | B482: 3 | C482: MEDIANA LOTUS | E482: DANIELA
A483: 46120 | B483: 3 | C483: MINI PISTACHO | E483: DANIELA
... A517: 46123 | B517: 6 | C517: PORCION OG | E517: DANIELA
A518: 46123 | B518: 7 | C518: MINI LOTUS | D518: 2 PDV | E518: DANIELA
A519: 46123 | B519: 2 | C519: MEDIANA LOTUS | E519: DANIELA
A520: 46123 | B520: 1 | C520: MINI PISTACHO | D520: 1 PDV | E520: DANIELA
A521: 46123 | B521: 8 | C521: CUCHAREABLE LOTUS | D521: 1 PDV | E521: DANIELA
A522: 46123 | B522: 8 | C522: CUCHAREABLE MILO | D522: 2 PDV | E522: DANIELA
A523: 46123 | B523: 8 | C523: CUCHAREABLE AREQUIPE | D523: 2 PDV | E523: DANIELA
A524: 46123 | B524: 1 | C524: CUCHAREABLE PISTACHO | E524: DANIELA
A525: 46125 | B525: 23 | C525: GRANDE OG | E525: DANIELA
A526: 46125 | B526: 19 | C526: MEDIANA OG | E526: DANIELA
A527: 46125 | B527: 16 | C527: MINI OG | E527: DANIELA
A528: 46125 | B528: 5 | C528: PORCION OG | E528: DANIELA
A529: 46125 | B529: 6 | C529: MINI LOTUS | E529: DANIELA
A530: 46125 | B530: 1 | C530: MEDIANA LOTUS | E530: DANIELA
A531: 46125 | B531: 1 | C531: MINI PISTACHO | E531: DANIELA
A532: 46125 | B532: 13 | C532: CUCHAREABLE LOTUS | E532: DANIELA
A533: 46125 | B533: 13 | C533: CUCHAREABLE MILO | E533: DANIELA
A534: 46125 | B534: 13 | C534: CUCHAREABLE AREQUIPE | E534: DANIELA
A535: 46125 | B535: 5 | C535: CUCHAREABLE PISTACHO | E535: DANIELA
... A539: 46126 | B539: 3 | C539: PORCION OG | E539: DANIELA
A540: 46126 | B540: 5 | C540: MINI LOTUS | D540: 1 POR PDV | E540: DANIELA
A541: 46126 | B541: 1 | C541: MEDIANA LOTUS | E541: DANIELA
A542: 46126 | B542: 2 | C542: BITES X4 OG | E542: DANIELA
A543: 46126 | B543: 13 | C543: CUCHAREABLE LOTUS | E543: DANIELA
A544: 46126 | B544: 12 | C544: CUCHAREABLE MILO | E544: DANIELA
A545: 46126 | B545: 12 | C545: CUCHAREABLE AREQUIPE | D545: 1 POR PDV | E545: DANIELA
A546: 46126 | B546: 4 | C546: CUCHAREABLE PISTACHO | E546: DANIELA
A547: 46127 | B547: 24 | C547: GRANDE OG | E547: DANIELA
A548: 46127 | B548: 25 | C548: MEDIANA OG | E548: DANIELA
A549: 46127 | B549: 17 | C549: MINI OG | E549: DANIELA
A550: 46127 | B550: 11 | C550: PORCION OG | E550: DANIELA
...

Sheet PRODUCCION
A1: FECHA | B1: CANTIDAD | C1: PRODUCTO | D1: COMENTARIOS | E1: INGRESADO
A2: 46025 | B2: 20 | C2: GRANDE OG | E2: OK
A3: 46025 | B3: 10 | C3: MINI OG | E3: OK
A4: 46025 | B4: 2 | C4: MEDIANA LOTUS | E4: OK
A5: 46025 | B5: 12 | C5: PORCION OG | D5: SE PORCIONA 1 GRANDE X12 | E5: OK
A6: 46027 | B6: 20 | C6: MEDIANA OG | E6: OK
A7: 46027 | B7: 10 | C7: MINI OG | E7: OK
A8: 46028 | B8: 15 | C8: MEDIANA OG | E8: OK
A9: 46028 | B9: 15 | C9: MINI OG | E9: OK
A10: 46028 | B10: 3 | C10: BITES X4 OG | E10: OK
A11: 46028 | B11: 79 | C11: MASA GALLETA DE BITES | E11: OK
A12: 46029 | B12: 15 | C12: GRANDE OG | E12: OK
A13: 46029 | B13: 10 | C13: MEDIANA OG | E13: OK
A14: 46029 | B14: 12 | C14: PORCION OG | D14: SE PORCIONA 1 GRANDE X12 | E14: OK
A15: 46030 | B15: 2 | C15: BITES X4 OG | E15: OK
A16: 46030 | B16: 15 | C16: GRANDE OG | E16: OK
A17: 46030 | B17: 15 | C17: MINI OG | E17: OK
A18: 46030 | B18: 1 | C18: MEDIANA LOTUS | E18: OK
A19: 46032 | B19: 3 | C19: BITES X4 OG | E19: OK
A20: 46032 | B20: 10 | C20: MINI OG | E20: OK
A21: 46032 | B21: 10 | C21: MEDIANA OG | E21: OK
A22: 46032 | B22: 10 | C22: GRANDE OG | E22: OK
A23: 46031 | B23: 1 | C23: MEDIANA VAINILLA | E23: OK
A24: 46035 | B24: 21 | C24: MEDIANA OG | E24: OK
A25: 46035 | B25: 5 | C25: GRANDE OG | E25: OK
A26: 46035 | B26: 10 | C26: MINI OG | E26: OK
... A36: 46037 | B36: 2 | C36: MINI PISTACHO | E36: OK
A37: 46037 | B37: 12 | C37: PORCION OG | D37: SE PORCIONA 1 GRANDE X12 | E37: OK
A38: 46037 | B38: 1 | C38: GRANDE LIMON | E38: OK
A39: 46038 | B39: 4 | C39: BITES X4 NUTELLA | D39: INDIVIDUALES / NUTELLA | E39: OK
A40: 46038 | B40: 4 | C40: BITES X4 VAINILLA MADAGASCAR | D40: INDIVIDUALES / VAINILLA | E40: OK
A41: 46038 | B41: 4 | C41: BITES X4 OG | D41: INDIVIDUALES / ORIGINAL | E41: OK
A42: 46038 | B42: 4 | C42: BITES X4 PISTACHO | D42: INDIVIDUALES / PISTACHOS | E42: OK
A43: 46038 | B43: 4 | C43: BITES X4 LOTUS | D43: INDIVIDUALES / LOTUS | E43: OK
A44: 46038 | B44: 4 | C44: BITES X4 OG | D44: INDIVIDUALES / ORIGINAL + AREQUIPE | E44: OK
A45: 46038 | B45: 1 | C45: GALLETA CHIPS CHOCOLATE X35 | E45: OK
A46: 46038 | B46: 1 | C46: GALLETA CHIPS CHOCOLATE BLANCO X35 | E46: OK
A47: 46038 | B47: 1 | C47: GRANDE VAINILLA | E47: OK
A48: 46038 | B48: 1 | C48: MEDIANA LOTUS | E48: OK
A49: 46039 | B49: 10 | C49: MINI OG | E49: OK
A50: 46039 | B50: 15 | C50: MEDIANA OG | E50: OK
A51: 46039 | B51: 15 | C51: GRANDE OG | E51: OK
A52: 46041 | B52: 1 | C52: GRANDE OG | D52: SE DESCUENTA, NO PASA CALIDAD | E52: OK
A53: 46041 | B53: 1 | C53: MINI OG | D53: PARA PRUEBAS / SE HACE LA MEZCLA | E53: OK
A54: 46041 | B54: 1 | C54: MEDIANA OG | D54: PARA PRUEBAS / SE HACE LA MEZCLA | E54: OK
A55: 46041 | B55: 1 | C55: GRANDE OG | D55: PARA PRUEBAS / SE HACE LA MEZCLA | E55: OK
A56: 46041 | B56: 10 | C56: PORCION OG | D56: SE PORCIONA 1 GRANDE X12 | E56: OK
A57: 46042 | B57: 1 | C57: MEDIANA LOTUS | E57: OK
A58: 46043 | B58: 30 | C58: BITES X4 OG | E58: OK
A59: 46043 | B59: 1 | C59: MEDIANA PISTACHO | E59: OK
A60: 46043 | B60: 15 | C60: MINI OG | E60: OK
A61: 46043 | B61: 20 | C61: GRANDE OG | E61: OK
A62: 46043 | B62: 15 | C62: MEDIANA OG | E62: OK
A63: 46043 | B63: 4 | C63: MINI LOTUS | E63: OK
A64: 46043 | B64: 2 | C64: MINI PISTACHO | E64: OK
A65: 46043 | B65: 1 | C65: GRANDE OG | D65: DESCONTAR, SE RIEGA EN EL HORNO | E65: OK
A66: 46044 | B66: 25 | C66: MINI ORIGINAL VELEZ CAFE | E66: OK
A67: 46044 | B67: 27 | C67: MINI PISTACHO VELEZ CAFE | E67: OK
A68: 46044 | B68: 3 | C68: MINI MILO CAFE VELEZ CAFE | E68: OK
A69: 46044 | B69: 10 | C69: MINI OG | E69: OK
A70: 46044 | B70: 10 | C70: GRANDE OG | E70: OK
A71: 46044 | B71: 12 | C71: PORCION OG | D71: SE PORCIONA 1 GRANDE X12 | E71: OK
A72: 46044 | B72: 1 | C72: MINI OG | D72: SALIO DE MAS EN PRODUCCION | E72: OK
A73: 46045 | B73: 10 | C73: MEDIANA OG | E73: OK
A74: 46045 | B74: 10 | C74: GRANDE OG | E74: OK
A75: 46045 | B75: 1 | C75: GRANDE MILO | E75: OK
A76: 46046 | B76: 1 | C76: MEDIANA LOTUS | E76: OK
A77: 46046 | B77: 12 | C77: PORCION OG | D77: SE PORCIONA 1 GRANDE X12 | E77: OK
A78: 46048 | B78: 2 | C78: BITES X4 OG | E78: OK
A79: 46049 | B79: 1 | C79: GRANDE VAINILLA | E79: OK
A80: 46049 | B80: 15 | C80: MEDIANA OG | E80: OK
A81: 46049 | B81: 10 | C81: MINI OG | E81: OK
A82: 46049 | B82: 6 | C82: GRANDE OG | E82: OK
A83: 46049 | B83: 1 | C83: GRANDE ORIGINAL X COOKIE WORLD | D83: PRUEBA CON BASE DE CACAO | E83: OK
A84: 46049 | B84: 1 | C84: MEDIANA ORIGINAL X COOKIE WORLD | D84: PRUEBA CON BASE DE CACAO | E84: OK
A85: 46049 | B85: 1 | C85: MINI ORIGINAL X COOKIE WORLD | D85: PRUEBA CON BASE DE CACAO | E85: OK
A86: 46049 | B86: 1 | C86: MINI VAINILLA | E86: OK
A87: 46050 | B87: 10 | C87: GRANDE OG | E87: OK
A88: 46050 | B88: 10 | C88: MEDIANA OG | E88: OK
A89: 46050 | B89: 10 | C89: MINI OG | E89: OK
A90: 46050 | B90: 2 | C90: MINI LOTUS | E90: OK
A91: 46050 | B91: 1 | C91: MINI PISTACHO | E91: OK
A92: 46050 | B92: 12 | C92: PORCION OG | D92: SE PORCIONA 1 GRANDE X12 | E92: OK
A93: 46050 | B93: 1 | C93: GRANDE VAINILLA | E93: OK
A94: 46050 | B94: 1 | C94: MEDIANA PISTACHO | E94: OK
A95: 46051 | B95: 10 | C95: BITES X4 OG | E95: OK
A96: 46051 | B96: 10 | C96: GRANDE OG | E96: OK
A97: 46051 | B97: 1 | C97: MINI VAINILLA | E97: OK
A98: 46051 | B98: 1 | C98: MINI LOTUS | E98: OK
A99: 46051 | B99: 1 | C99: MINI MILO | E99: OK
A100: 46051 | B100: 1 | C100: MEDIANA VAINILLA | E100: OK
A101: 46052 | B101: 10 | C101: GRANDE OG | E101: OK
A102: 46052 | B102: 8 | C102: MEDIANA OG | E102: OK
A103: 46052 | B103: 10 | C103: MINI OG | E103: OK
A104: 46052 | B104: 3 | C104: BITES X4 OG | E104: OK
A105: 46052 | B105: 1 | C105: GRANDE LIMON | E105: OK
A106: 46052 | B106: 12 | C106: PORCION OG | D106: SE PORCIONA 1 GRANDE X12 | E106: OK
A107: 46053 | B107: 10 | C107: GRANDE OG | E107: OK
A108: 46053 | B108: 10 | C108: MEDIANA OG | E108: OK
A109: 46053 | B109: 10 | C109: MINI OG | E109: OK
...

Sheet TRASLADOS BODEGAS
A1: FECHA | B1: CANTIDAD | C1: PRODUCTO | D1: COMENTARIOS | E1: INGRESADO
A2: 46010 | B2: 4 | C2: MEDIANA OG | E2: OK
A3: 46010 | B3: 5 | C3: GRANDE OG | D3: 2 CAJA BLANCA X12 | E3: OK
A4: 46011 | B4: 4 | C4: GRANDE OG | D4: MARCADA X12 | E4: OK
A5: 46015 | B5: 5 | C5: GRANDE OG | D5: MARCADA X12 | E5: OK
A6: 46015 | B6: 3 | C6: GRANDE NAVIDAD | E6: OK
A7: 46014 | B7: 6 | C7: MINI OG | E7: OK
A8: 46014 | B8: 4 | C8: MINI NAVIDAD | E8: OK
A9: 46016 | B9: 4 | C9: GRANDE OG | D9: MARCADA X12 | E9: OK
A10: 46016 | B10: 2 | C10: MEDIANA OG | E10: OK
A11: 46016 | B11: 2 | C11: MEDIANA NAVIDAD | E11: OK
A12: 46016 | B12: 2 | C12: MINI OG | E12: OK
A13: 46016 | B13: 4 | C13: MINI NAVIDAD | E13: OK
A14: 46018 | B14: 4 | C14: MINI OG | E14: OK
A15: 46018 | B15: 4 | C15: MINI NAVIDAD | E15: OK
A16: 46018 | B16: 4 | C16: MEDIANA OG | E16: OK
A17: 46018 | B17: 4 | C17: MEDIANA NAVIDAD | E17: OK
A18: 46018 | B18: 4 | C18: GRANDE OG | D18: MARCADA X12 CAJA BLANCA | E18: OK
A19: 46020 | B19: 5 | C19: MINI OG | E19: OK
A20: 46020 | B20: 10 | C20: GRANDE OG | D20: MARCADA X12 | E20: OK
A21: 46021 | B21: 6 | C21: GRANDE OG | D21: MARCADA X12 3 SE PORCIONAN | E21: OK
A22: 46021 | B22: 7 | C22: MEDIANA OG | E22: OK
A23: 46024 | B23: 6 | C23: MINI OG | E23: OK
A24: 46024 | B24: 6 | C24: MEDIANA OG | E24: OK
A25: 46024 | B25: 3 | C25: GRANDE OG | D25: MARCADA X12 | E25: OK
A26: 46025 | B26: 10 | C26: GRANDE OG | D26: MARCADA X12 | E26: OK
A27: 46025 | B27: 5 | C27: MINI OG | E27: OK
A28: 46029 | B28: 6 | C28: GRANDE OG | D28: x12 / 3 EN CAJA BLANCA | E28: OK
A29: 46029 | B29: 4 | C29: MEDIANA OG | E29: OK
A30: 46029 | B30: 3 | C30: MEDIANA NAVIDAD | E30: OK
A31: 46029 | B31: 2 | C31: MINI OG | E31: OK
A32: 46029 | B32: 3 | C32: MINI NAVIDAD | E32: OK
A33: 46031 | B33: 4 | C33: MEDIANA NAVIDAD | E33: OK
A34: 46031 | B34: 2 | C34: MEDIANA OG | E34: OK
A35: 46031 | B35: 6 | C35: GRANDE OG | D35: MARCADA X12 | E35: OK
A36: 46037 | B36: 4 | C36: GRANDE OG | D36: MARCADA X12 | E36: OK
A37: 46037 | B37: 4 | C37: MEDIANA OG | E37: OK
A38: 46037 | B38: 6 | C38: MINI OG | E38: OK
A39: 46039 | B39: 4 | C39: MINI OG | E39: OK
A40: 46039 | B40: 8 | C40: GRANDE OG | D40: MARCADA X12 | E40: OK
A41: 46044 | B41: 10 | C41: GRANDE OG | D41: MARCADA X12 | E41: OK
A42: 46044 | B42: 6 | C42: MEDIANA OG | E42: OK
A43: 46044 | B43: 6 | C43: MINI OG | E43: OK
A44: 46044 | B44: 1 | D44: PAQ. BOLSAS BLANCAS X100 | E44: OK
A45: 46044 | B45: 1 | D45: PAQ. BLONDAS X100 | E45: OK
A46: 46050 | B46: 5 | C46: GRANDE OG | D46: MARCADA X12 | E46: OK
A47: 46050 | B47: 5 | C47: MEDIANA OG | E47: OK
A48: 46050 | B48: 5 | C48: MINI OG | E48: OK
A49: 46052 | B49: 5 | C49: GRANDE OG | D49: MARCADA X12 | E49: OK
A50: 46052 | B50: 4 | C50: MEDIANA OG | E50: OK
A51: 46057 | B51: 4 | C51: MINI OG | E51: OK
A52: 46058 | B52: 7 | C52: MINI OG | E52: OK
A53: 46058 | B53: 7 | C53: GRANDE OG | D53: MARCADA X12 | E53: OK
A54: 46062 | B54: 6 | C54: MINI OG | E54: OK
A55: 46062 | B55: 9 | C55: GRANDE OG | D55: MARCADA X12 | E55: OK
A56: 46065 | B56: 6 | C56: MINI OG | E56: OK
A57: 46065 | B57: 4 | C57: GRANDE OG | D57: MARCADA X12 | E57: OK
A58: 46069 | B58: 8 | C58: MINI OG | E58: OK
A59: 46069 | B59: 4 | C59: MEDIANA OG | E59: OK
A60: 46069 | B60: 9 | C60: GRANDE OG | D60: MARCADA X12 | E60: OK
A61: 46072 | B61: 3 | C61: MEDIANA OG | E61: OK
A62: 46076 | B62: 8 | C62: GRANDE OG | D62: MARCADA X12 | E62: OK
A63: 46076 | B63: 4 | C63: MEDIANA OG | E63: OK
A64: 46076 | B64: 6 | C64: MINI OG | E64: OK
A65: 46081 | B65: 7 | C65: MINI OG | E65: OK
A66: 46081 | B66: 4 | C66: MEDIANA OG | E66: OK
A67: 46081 | B67: 8 | C67: GRANDE OG | D67: MARCADA X12 | E67: OK
A68: 46084 | B68: 4 | C68: MINI OG | E68: OK
A69: 46084 | B69: 3 | C69: MEDIANA OG | E69: OK
A70: 46084 | B70: 1 | D70: BOLSAS AZULES (100) | E70: OK
A71: 46084 | B71: 1 | D71: BOLSAS BLANCAS (100) | E71: OK
A72: 46086 | B72: 9 | C72: GRANDE OG | D72: MARCADA X12 | E72: OK
A73: 46086 | B73: 50 | D73: BLONDAS MINI | E73: OK
A74: 46086 | B74: 50 | D74: CAJA AZUL MINI | E74: OK
A75: 46091 | B75: 9 | C75: GRANDE OG | E75: OK
A76: 46091 | B76: 4 | C76: MEDIANA OG | E76: OK
A77: 46091 | B77: 9 | C77: MINI OG | E77: OK
A78: 46095 | B78: 5 | C78: GRANDE OG | E78: OK
A79: 46095 | B79: 2 | C79: MEDIANA OG | E79: OK
A80: 46097 | B80: 3 | C80: GRANDE OG | D80: NT19 | E80: OK
A81: 46097 | B81: 3 | C81: MEDIANA OG | D81: NT19 | E81: OK
A82: 46097 | B82: 5 | C82: MINI OG | D82: NT19 | E82: OK
A83: 46100 | B83: 8 | C83: GRANDE OG | D83: NT20 | E83: OK
A84: 46105 | B84: 5 | C84: GRANDE OG | D84: NT21 | E84: OK
A85: 46105 | B85: 4 | C85: MEDIANA OG | D85: NT21 | E85: OK
A86: 46105 | B86: 6 | C86: MINI OG | D86: NT21 | E86: OK
A87: 46109 | B87: 8 | C87: GRANDE OG | D87: NT22 | E87: OK
A88: 46109 | B88: 4 | C88: MEDIANA OG | D88: NT22 | E88: OK
A89: 46109 | B89: 5 | C89: MINI OG | D89: NT22 | E89: OK
A90: 46112 | B90: 4 | C90: GRANDE OG | D90: NT23 | E90: OK
A91: 46112 | B91: 4 | C91: MEDIANA OG | D91: NT23 | E91: OK
... A96: 46119 | B96: 5 | C96: GRANDE OG | D96: NT25 | E96: OK
A97: 46119 | B97: 5 | C97: MEDIANA OG | D97: NT25 | E97: OK | V97: /
A98: 46119 | B98: 6 | C98: MINI OG | D98: NT25 | E98: OK
A99: 46122 | B99: 5 | C99: GRANDE OG | D99: NT26 | E99: OK
A100: 46122 | B100: 4 | C100: MEDIANA OG | D100: NT26 | E100: OK
A101: 46122 | B101: 4 | C101: MINI OG | D101: NT26 | E101: OK
A102: 46128 | B102: 5 | C102: GRANDE OG | D102: NT27 | E102: OK
A103: 46128 | B103: 4 | C103: MEDIANA OG | D103: NT27 | E103: OK
A104: 46128 | B104: 6 | C104: MINI OG | D104: NT27 | E104: OK
...

Sheet PEDIDOS
A1: CLIENTE | B1: FECHA DE ENTREGA | C1: CANTIDAD | D1: PRODUCTO | E1: COMENTARIOS (SI ES REGALO, HORA DE ENTREGA ESPECIFICA, MARCADO X ALGO) | F1: METODO DE PAGO | G1: DOMICILIO | H1: DOMICILIARIO | I1: DOMICILIO COBRO A CLIENTE | J1: PRECIO TOTAL | K1: PAGO DOMICILIO REAL | L1: FACTURA ELECTRONICA | M1: ENTREGADO | N1: TRASLADADO
A2: AMBIENTE LIVING | B2: 46024 | C2: 1 | D2: GRANDE OG | E2: MARCAD X10 | G2: SI | H2: INDRIVE | I2: 8000 | J2: =IF(A2="RAPPI",(VLOOKUP(TRIM(D2), CATALOGO!F:G, 2, FALSE) * C2)+I2,IFERROR(IF(COUNTIF('RESTAURANTESDESCUENTOS 2026'!A:A,TRIM(A2))>0,((VLOOKUP(TRIM(D2), CATALOGO!A:B, 2, FALSE) * C2)*(1-VALUE(SUBSTITUTE(VLOOKUP(TRIM(A2),'RESTAURANTESDESCUENTOS 2026'!A:B,2,FALSE),"%",""))/100)+I2),(VLOOKUP(TRIM(D2), CATALOGO!A:B, 2, FALSE) * C2+I2)),"")) -> 105125 | K2: 10000 | L2: SI | M2: SI
A3: AZUL SELVA | B3: 46024 | C3: 1 | D3: GRANDE OG | E3: MARCADA X12 | G3: SI | H3: INDRIVE | I3: 0 | J3: =IF(A3="RAPPI",(VLOOKUP(TRIM(D3), CATALOGO!F:G, 2, FALSE) * C3)+I3,IFERROR(IF(COUNTIF('RESTAURANTESDESCUENTOS 2026'!A:A,TRIM(A3))>0,((VLOOKUP(TRIM(D3), CATALOGO!A:B, 2, FALSE) * C3)*(1-VALUE(SUBSTITUTE(VLOOKUP(TRIM(A3),'RESTAURANTESDESCUENTOS 2026'!A:B,2,FALSE),"%",""))/100)+I3),(VLOOKUP(TRIM(D3), CATALOGO!A:B, 2, FALSE) * C3+I3)),"")) -> 112500 | K3: 10000 | L3: SI | M3: SI
A4: REGINA ROJAS | B4: 46024 | C4: 1 | D4: MEDIANA NAVIDAD | E4: NAVIDAD | G4: SI | H4: INDRIVE | I4: 14000 | J4: =IF(A4="RAPPI",(VLOOKUP(TRIM(D4), CATALOGO!F:G, 2, FALSE) * C4)+I4,IFERROR(IF(COUNTIF('RESTAURANTESDESCUENTOS 2026'!A:A,TRIM(A4))>0,((VLOOKUP(TRIM(D4), CATALOGO!A:B, 2, FALSE) * C4)*(1-VALUE(SUBSTITUTE(VLOOKUP(TRIM(A4),'RESTAURANTESDESCUENTOS 2026'!A:B,2,FALSE),"%",""))/100)+I4),(VLOOKUP(TRIM(D4), CATALOGO!A:B, 2, FALSE) * C4+I4)),"")) -> 137000 | K4: 14000 | M4: SI
A5: MIGUEL ANGEL VERA | B5: 46024 | C5: 1 | D5: MEDIANA OG | G5: SI | H5: INDRIVE | I5: 12000 | J5: =IF(A5="RAPPI",(VLOOKUP(TRIM(D5), CATALOGO!F:G, 2, FALSE) * C5)+I5,IFERROR(IF(COUNTIF('RESTAURANTESDESCUENTOS 2026'!A:A,TRIM(A5))>0,((VLOOKUP(TRIM(D5), CATALOGO!A:B, 2, FALSE) * C5)*(1-VALUE(SUBSTITUTE(VLOOKUP(TRIM(A5),'RESTAURANTESDESCUENTOS 2026'!A:B,2,FALSE),"%",""))/100)+I5),(VLOOKUP(TRIM(D5), CATALOGO!A:B, 2, FALSE) * C5+I5)),"")) -> 127000 | K5: 12000 | M5: SI
A6: CASA FLORA | B6: 46024 | C6: 1 | D6: GRANDE OG | E6: MARCADA X12 / YA ESTA DESPACHADO | G6: SI | H6: INDRIVE | I6: 0 | J6: =IF(A6="RAPPI",(VLOOKUP(TRIM(D6), CATALOGO!F:G, 2, FALSE) * C6)+I6,IFERROR(IF(COUNTIF('RESTAURANTESDESCUENTOS 2026'!A:A,TRIM(A6))>0,((VLOOKUP(TRIM(D6), CATALOGO!A:B, 2, FALSE) * C6)*(1-VALUE(SUBSTITUTE(VLOOKUP(TRIM(A6),'RESTAURANTESDESCUENTOS 2026'!A:B,2,FALSE),"%",""))/100)+I6),(VLOOKUP(TRIM(D6), CATALOGO!A:B, 2, FALSE) * C6+I6)),"")) -> 105000 | K6: 0 | L6: SI | M6: SI
A7: BARBARO RIONEGRO | B7: 46024 | C7: 3 | D7: MEDIANA OG | E7: RIONEGRO / MARCADA X10 | G7: SI | H7: INDRIVE | I7: 0 | J7: =IF(A7="RAPPI",(VLOOKUP(TRIM(D7), CATALOGO!F:G, 2, FALSE) * C7)+I7,IFERROR(IF(COUNTIF('RESTAURANTESDESCUENTOS 2026'!A:A,TRIM(A7))>0,((VLOOKUP(TRIM(D7), CATALOGO!A:B, 2, FALSE) * C7)*(1-VALUE(SUBSTITUTE(VLOOKUP(TRIM(A7),'RESTAURANTESDESCUENTOS 2026'!A:B,2,FALSE),"%",""))/100)+I7),(VLOOKUP(TRIM(D7), CATALOGO!A:B, 2, FALSE) * C7+I7)),"")) -> 258750 | K7: 0 | L7: SI | M7: SI
A8: CAMILO ALVAREZ | B8: 46024 | C8: 1 | D8: GRANDE VAINILLA | G8: NO | J8: =IF(A8="RAPPI",(VLOOKUP(TRIM(D8), CATALOGO!F:G, 2, FALSE) * C8)+I8,IFERROR(IF(COUNTIF('RESTAURANTESDESCUENTOS 2026'!A:A,TRIM(A8))>0,((VLOOKUP(TRIM(D8), CATALOGO!A:B, 2, FALSE) * C8)*(1-VALUE(SUBSTITUTE(VLOOKUP(TRIM(A8),'RESTAURANTESDESCUENTOS 2026'!A:B,2,FALSE),"%",""))/100)+I8),(VLOOKUP(TRIM(D8), CATALOGO!A:B, 2, FALSE) * C8+I8)),"")) -> 163000 | M8: SI
A9: LA ABUELA NITA | B9: 46024 | C9: 2 | D9: GRANDE OG | E9: MARCADA X12 | G9: SI | H9: INDRIVE | I9: 0 | J9: =IF(A9="RAPPI",(VLOOKUP(TRIM(D9), CATALOGO!F:G, 2, FALSE) * C9)+I9,IFERROR(IF(COUNTIF('RESTAURANTESDESCUENTOS 2026'!A:A,TRIM(A9))>0,((VLOOKUP(TRIM(D9), CATALOGO!A:B, 2, FALSE) * C9)*(1-VALUE(SUBSTITUTE(VLOOKUP(TRIM(A9),'RESTAURANTESDESCUENTOS 2026'!A:B,2,FALSE),"%",""))/100)+I9),(VLOOKUP(TRIM(D9), CATALOGO!A:B, 2, FALSE) * C9+I9)),"")) -> 225000 | K9: 0 | L9: SI | M9: SI
A10: PDV | B10: 46024 | C10: 6 | D10: MINI OG | G10: SI | H10: INDRIVE | I10: 0 | J10: 0 | K10: 170000 | M10: SI
A11: CESAR JIMENEZ | B11: 46024 | C11: 1 | D11: PORCION OG | G11: SI | H11: INDRIVE | I11: 10000 | J11: =IF(A11="RAPPI",(VLOOKUP(TRIM(D11), CATALOGO!F:G, 2, FALSE) * C11)+I11,IFERROR(IF(COUNTIF('RESTAURANTESDESCUENTOS 2026'!A:A,TRIM(A11))>0,((VLOOKUP(TRIM(D11), CATALOGO!A:B, 2, FALSE) * C11)*(1-VALUE(SUBSTITUTE(VLOOKUP(TRIM(A11),'RESTAURANTESDESCUENTOS 2026'!A:B,2,FALSE),"%",""))/100)+I11),(VLOOKUP(TRIM(D11), CATALOGO!A:B, 2, FALSE) * C11+I11)),"")) -> 28000 | K11: 10000 | M11: SI
A12: ANA MARIA OROZCO | B12: 46024 | C12: 1 | D12: MEDIANA OG | G12: SI | H12: INDRIVE | I12: 10000 | J12: =IF(A12="RAPPI",(VLOOKUP(TRIM(D12), CATALOGO!F:G, 2, FALSE) * C12)+I12,IFERROR(IF(COUNTIF('RESTAURANTESDESCUENTOS 2026'!A:A,TRIM(A12))>0,((VLOOKUP(TRIM(D12), CATALOGO!A:B, 2, FALSE) * C12)*(1-VALUE(SUBSTITUTE(VLOOKUP(TRIM(A12),'RESTAURANTESDESCUENTOS 2026'!A:B,2,FALSE),"%",""))/100)+I12),(VLOOKUP(TRIM(D12), CATALOGO!A:B, 2, FALSE) * C12+I12)),"")) -> 125000 | K12: 10000 | M12: SI
A13: LAURA HURTADO | B13: 46024 | C13: 1 | D13: MINI OG + AREQUIPE | G13: SI | H13: INDRIVE | I13: 13000 | J13: =IF(A13="RAPPI",(VLOOKUP(TRIM(D13), CATALOGO!F:G, 2, FALSE) * C13)+I13,IFERROR(IF(COUNTIF('RESTAURANTESDESCUENTOS 2026'!A:A,TRIM(A13))>0,((VLOOKUP(TRIM(D13), CATALOGO!A:B, 2, FALSE) * C13)*(1-VALUE(SUBSTITUTE(VLOOKUP(TRIM(A13),'RESTAURANTESDESCUENTOS 2026'!A:B,2,FALSE),"%",""))/100)+I13),(VLOOKUP(TRIM(D13), CATALOGO!A:B, 2, FALSE) * C13+I13)),"")) -> 66000 | K13: 13000 | M13: SI
A14: PDV | B14: 46024 | C14: 3 | D14: GRANDE OG | E14: MARCADA X12 | G14: SI | H14: INDRIVE | I14: 0 | J14: 0 | K14: 0 | M14: SI
A15: PDV | B15: 46024 | C15: 6 | D15: MEDIANA OG | G15: SI | H15: INDRIVE | I15: 0 | J15: 0 | K15: 0 | M15: SI
A16: CESAR JIMENEZ | B16: 46024 | C16: 1 | D16: PORCION OG + FRUTOS ROJOS | G16: SI | H16: INDRIVE | I16: 0 | J16: =IF(A16="RAPPI",(VLOOKUP(TRIM(D16), CATALOGO!F:G, 2, FALSE) * C16)+I16,IFERROR(IF(COUNTIF('RESTAURANTESDESCUENTOS 2026'!A:A,TRIM(A16))>0,((VLOOKUP(TRIM(D16), CATALOGO!A:B, 2, FALSE) * C16)*(1-VALUE(SUBSTITUTE(VLOOKUP(TRIM(A16),'RESTAURANTESDESCUENTOS 2026'!A:B,2,FALSE),"%",""))/100)+I16),(VLOOKUP(TRIM(D16), CATALOGO!A:B, 2, FALSE) * C16+I16)),"")) -> 22000 | K16: 0 | M16: SI
A17: RAPPI | B17: 46024 | C17: 1 | D17: GRANDE NAVIDAD | E17: 7468 | G17: SI | H17: RAPPI | J17: =IF(A17="RAPPI",(VLOOKUP(TRIM(D17), CATALOGO!F:G, 2, FALSE) * C17)+I17,IFERROR(IF(COUNTIF('RESTAURANTESDESCUENTOS 2026'!A:A,TRIM(A17))>0,((VLOOKUP(TRIM(D17), CATALOGO!A:B, 2, FALSE) * C17)*(1-VALUE(SUBSTITUTE(VLOOKUP(TRIM(A17),'RESTAURANTESDESCUENTOS 2026'!A:B,2,FALSE),"%",""))/100)+I17),(VLOOKUP(TRIM(D17), CATALOGO!A:B, 2, FALSE) * C17+I17)),"")) -> 163000 | M17: SI
A18: RAPPI | B18: 46024 | C18: 1 | D18: MINI NAVIDAD | E18: 340 | G18: SI | H18: RAPPI | J18: =IF(A18="RAPPI",(VLOOKUP(TRIM(D18), CATALOGO!F:G, 2, FALSE) * C18)+I18,IFERROR(IF(COUNTIF('RESTAURANTESDESCUENTOS 2026'!A:A,TRIM(A18))>0,((VLOOKUP(TRIM(D18), CATALOGO!A:B, 2, FALSE) * C18)*(1-VALUE(SUBSTITUTE(VLOOKUP(TRIM(A18),'RESTAURANTESDESCUENTOS 2026'!A:B,2,FALSE),"%",""))/100)+I18),(VLOOKUP(TRIM(D18), CATALOGO!A:B, 2, FALSE) * C18+I18)),"")) -> 53000 | M18: SI
A19: RAPPI | B19: 46024 | C19: 1 | D19: PORCION OG + NUTELLA | E19: 635 | G19: SI | H19: RAPPI | J19: =IF(A19="RAPPI",(VLOOKUP(TRIM(D19), CATALOGO!F:G, 2, FALSE) * C19)+I19,IFERROR(IF(COUNTIF('RESTAURANTESDESCUENTOS 2026'!A:A,TRIM(A19))>0,((VLOOKUP(TRIM(D19), CATALOGO!A:B, 2, FALSE) * C19)*(1-VALUE(SUBSTITUTE(VLOOKUP(TRIM(A19),'RESTAURANTESDESCUENTOS 2026'!A:B,2,FALSE),"%",""))/100)+I19),(VLOOKUP(TRIM(D19), CATALOGO!A:B, 2, FALSE) * C19+I19)),"")) -> 22000 | M19: SI
A20: RAPPI | B20: 46024 | C20: 1 | D20: PORCION OG + FRUTOS ROJOS | E20: 7333 | G20: SI | H20: RAPPI | J20: =IF(A20="RAPPI",(VLOOKUP(TRIM(D20), CATALOGO!F:G, 2, FALSE) * C20)+I20,IFERROR(IF(COUNTIF('RESTAURANTESDESCUENTOS 2026'!A:A,TRIM(A20))>0,((VLOOKUP(TRIM(D20), CATALOGO!A:B, 2, FALSE) * C20)*(1-VALUE(SUBSTITUTE(VLOOKUP(TRIM(A20),'RESTAURANTESDESCUENTOS 2026'!A:B,2,FALSE),"%",""))/100)+I20),(VLOOKUP(TRIM(D20), CATALOGO!A:B, 2, FALSE) * C20+I20)),"")) -> 22000 | M20: SI
A21: VENTA EN LOCAL | B21: 46024 | C21: 1 | D21: MINI NAVIDAD | E21: PAGO EN EFECTIVO | G21: NO | J21: =IF(A21="RAPPI",(VLOOKUP(TRIM(D21), CATALOGO!F:G, 2, FALSE) * C21)+I21,IFERROR(IF(COUNTIF('RESTAURANTESDESCUENTOS 2026'!A:A,TRIM(A21))>0,((VLOOKUP(TRIM(D21), CATALOGO!A:B, 2, FALSE) * C21)*(1-VALUE(SUBSTITUTE(VLOOKUP(TRIM(A21),'RESTAURANTESDESCUENTOS 2026'!A:B,2,FALSE),"%",""))/100)+I21),(VLOOKUP(TRIM(D21), CATALOGO!A:B, 2, FALSE) * C21+I21)),"")) -> 53000 | M21: SI
A22: VENTA EN LOCAL | B22: 46024 | C22: 1 | D22: MEDIANA OG | E22: PAGO EN TRANSFERENCIA | G22: NO | J22: =IF(A22="RAPPI",(VLOOKUP(TRIM(D22), CATALOGO!F:G, 2, FALSE) * C22)+I22,IFERROR(IF(COUNTIF('RESTAURANTESDESCUENTOS 2026'!A:A,TRIM(A22))>0,((VLOOKUP(TRIM(D22), CATALOGO!A:B, 2, FALSE) * C22)*(1-VALUE(SUBSTITUTE(VLOOKUP(TRIM(A22),'RESTAURANTESDESCUENTOS 2026'!A:B,2,FALSE),"%",""))/100)+I22),(VLOOKUP(TRIM(D22), CATALOGO!A:B, 2, FALSE) * C22+I22)),"")) -> 115000 | M22: SI
A23: VENTA EN LOCAL | B23: 46024 | C23: 1 | D23: PORCION OG | E23: PAGO EN TRANSFERENCIA | G23: NO | J23: =IF(A23="RAPPI",(VLOOKUP(TRIM(D23), CATALOGO!F:G, 2, FALSE) * C23)+I23,IFERROR(IF(COUNTIF('RESTAURANTESDESCUENTOS 2026'!A:A,TRIM(A23))>0,((VLOOKUP(TRIM(D23), CATALOGO!A:B, 2, FALSE) * C23)*(1-VALUE(SUBSTITUTE(VLOOKUP(TRIM(A23),'RESTAURANTESDESCUENTOS 2026'!A:B,2,FALSE),"%",""))/100)+I23),(VLOOKUP(TRIM(D23), CATALOGO!A:B, 2, FALSE) * C23+I23)),"")) -> 18000 | M23: SI
A24: ENTRECOTE BY CATA INDIANA | B24: 46025 | C24: 1 | D24: GRANDE OG | E24: INDIANA / MARCADA X10 | G24: SI | H24: INDRIVE | I24: 15000 | J24: =IF(A24="RAPPI",(VLOOKUP(TRIM(D24), CATALOGO!F:G, 2, FALSE) * C24)+I24,IFERROR(IF(COUNTIF('RESTAURANTESDESCUENTOS 2026'!A:A,TRIM(A24))>0,((VLOOKUP(TRIM(D24), CATALOGO!A:B, 2, FALSE) * C24)*(1-VALUE(SUBSTITUTE(VLOOKUP(TRIM(A24),'RESTAURANTESDESCUENTOS 2026'!A:B,2,FALSE),"%",""))/100)+I24),(VLOOKUP(TRIM(D24), CATALOGO!A:B, 2, FALSE) * C24+I24)),"")) -> 127500 | K24: 15000 | L24: SI | M24: SI
A25: LONDRES COCINA | B25: 46025 | C25: 2 | D25: GRANDE OG | E25: MARCADA X10 | G25: SI | H25: INDRIVE | I25: 10000 | J25: =IF(A25="RAPPI",(VLOOKUP(TRIM(D25), CATALOGO!F:G, 2, FALSE) * C25)+I25,IFERROR(IF(COUNTIF('RESTAURANTESDESCUENTOS 2026'!A:A,TRIM(A25))>0,((VLOOKUP(TRIM(D25), CATALOGO!A:B, 2, FALSE) * C25)*(1-VALUE(SUBSTITUTE(VLOOKUP(TRIM(A25),'RESTAURANTESDESCUENTOS 2026'!A:B,2,FALSE),"%",""))/100)+I25),(VLOOKUP(TRIM(D25), CATALOGO!A:B, 2, FALSE) * C25+I25)),"")) -> 310000 | K25: 14000 | L25: SI | M25: SI
A26: ENTRECOTE BY CATA INTERPLAZA | B26: 46025 | C26: 1 | D26: GRANDE OG | E26: INTERPLAZA / MARCADA X10 | G26: SI | H26: INDRIVE | I26: 10000 | J26: =IF(A26="RAPPI",(VLOOKUP(TRIM(D26), CATALOGO!F:G, 2, FALSE) * C26)+I26,IFERROR(IF(COUNTIF('RESTAURANTESDESCUENTOS 2026'!A:A,TRIM(A26))>0,((VLOOKUP(TRIM(D26), CATALOGO!A:B, 2, FALSE) * C26)*(1-VALUE(SUBSTITUTE(VLOOKUP(TRIM(A26),'RESTAURANTESDESCUENTOS 2026'!A:B,2,FALSE),"%",""))/100)+I26),(VLOOKUP(TRIM(D26), CATALOGO!A:B, 2, FALSE) * C26+I26)),"")) -> 122500 | K26: 10000 | L26: SI | M26: SI
A27: CASA DE NADIE | B27: 46025 | C27: 3 | D27: GRANDE OG | E27: MARCADA X12 | G27: SI | H27: INDRIVE | I27: 10000 | J27: =IF(A27="RAPPI",(VLOOKUP(TRIM(D27), CATALOGO!F:G, 2, FALSE) * C27)+I27,IFERROR(IF(COUNTIF('RESTAURANTESDESCUENTOS 2026'!A:A,TRIM(A27))>0,((VLOOKUP(TRIM(D27), CATALOGO!A:B, 2, FALSE) * C27)*(1-VALUE(SUBSTITUTE(VLOOKUP(TRIM(A27),'RESTAURANTESDESCUENTOS 2026'!A:B,2,FALSE),"%",""))/100)+I27),(VLOOKUP(TRIM(D27), CATALOGO!A:B, 2, FALSE) * C27+I27)),"")) -> 347500 | K27: 10000 | L27: SI | M27: SI
A28: AMMAZZA LAURELES | B28: 46025 | C28: 1 | D28: MEDIANA OG | E28: LAURELES / MARCADA X10 | G28: SI | H28: INDRIVE | I28: 0 | J28: =IF(A28="RAPPI",(VLOOKUP(TRIM(D28), CATALOGO!F:G, 2, FALSE) * C28)+I28,IFERROR(IF(COUNTIF('RESTAURANTESDESCUENTOS 2026'!A:A,TRIM(A28))>0,((VLOOKUP(TRIM(D28), CATALOGO!A:B, 2, FALSE) * C28)*(1-VALUE(SUBSTITUTE(VLOOKUP(TRIM(A28),'RESTAURANTESDESCUENTOS 2026'!A:B,2,FALSE),"%",""))/100)+I28),(VLOOKUP(TRIM(D28), CATALOGO!A:B, 2, FALSE) * C28+I28)),"")) -> 86250 | K28: 13000 | L28: SI | M28: SI
A29: PDV | B29: 46025 | C29: 10 | D29: GRANDE OG | E29: MARCADA X12 | G29: SI | H29: DOMICILIARIO CARLOS | I29: 0 | J29: 0 | K29: 55000 | M29: SI
A30: ESTEFANIA CARDONA | B30: 46025 | C30: 1 | D30: MINI NAVIDAD | G30: SI | H30: INDRIVE | I30: 12000 | J30: =IF(A30="RAPPI",(VLOOKUP(TRIM(D30), CATALOGO!F:G, 2, FALSE) * C30)+I30,IFERROR(IF(COUNTIF('RESTAURANTESDESCUENTOS 2026'!A:A,TRIM(A30))>0,((VLOOKUP(TRIM(D30), CATALOGO!A:B, 2, FALSE) * C30)*(1-VALUE(SUBSTITUTE(VLOOKUP(TRIM(A30),'RESTAURANTESDESCUENTOS 2026'!A:B,2,FALSE),"%",""))/100)+I30),(VLOOKUP(TRIM(D30), CATALOGO!A:B, 2, FALSE) * C30+I30)),"")) -> 65000 | K30: 12000 | M30: SI
A31: VIVIANA GIRALDO | B31: 46025 | C31: 1 | D31: MEDIANA NAVIDAD | G31: SI | H31: INDRIVE | I31: 10000 | J31: =IF(A31="RAPPI",(VLOOKUP(TRIM(D31), CATALOGO!F:G, 2, FALSE) * C31)+I31,IFERROR(IF(COUNTIF('RESTAURANTESDESCUENTOS 2026'!A:A,TRIM(A31))>0,((VLOOKUP(TRIM(D31), CATALOGO!A:B, 2, FALSE) * C31)*(1-VALUE(SUBSTITUTE(VLOOKUP(TRIM(A31),'RESTAURANTESDESCUENTOS 2026'!A:B,2,FALSE),"%",""))/100)+I31),(VLOOKUP(TRIM(D31), CATALOGO!A:B, 2, FALSE) * C31+I31)),"")) -> 133000 | K31: 10000 | M31: SI
A32: NATALIA MARTINEZ | B32: 46025 | C32: 1 | D32: MEDIANA OG + NUTELLA | E32: NAVIDAD | G32: NO | J32: =IF(A32="RAPPI",(VLOOKUP(TRIM(D32), CATALOGO!F:G, 2, FALSE) * C32)+I32,IFERROR(IF(COUNTIF('RESTAURANTESDESCUENTOS 2026'!A:A,TRIM(A32))>0,((VLOOKUP(TRIM(D32), CATALOGO!A:B, 2, FALSE) * C32)*(1-VALUE(SUBSTITUTE(VLOOKUP(TRIM(A32),'RESTAURANTESDESCUENTOS 2026'!A:B,2,FALSE),"%",""))/100)+I32),(VLOOKUP(TRIM(D32), CATALOGO!A:B, 2, FALSE) * C32+I32)),"")) -> 123000 | M32: SI
A33: PDV | B33: 46025 | C33: 5 | D33: MINI OG | G33: SI | H33: DOMICILIARIO CARLOS | I33: 0 | J33: 0 | K33: 0 | M33: SI
A34: VENTA EN LOCAL | B34: 46025 | C34: 1 | D34: MINI OG + CREMA DE MILO | E34: PAGO EN EFECTIVO | G34: NO | J34: =IF(A34="RAPPI",(VLOOKUP(TRIM(D34), CATALOGO!F:G, 2, FALSE) * C34)+I34,IFERROR(IF(COUNTIF('RESTAURANTESDESCUENTOS 2026'!A:A,TRIM(A34))>0,((VLOOKUP(TRIM(D34), CATALOGO!A:B, 2, FALSE) * C34)*(1-VALUE(SUBSTITUTE(VLOOKUP(TRIM(A34),'RESTAURANTESDESCUENTOS 2026'!A:B,2,FALSE),"%",""))/100)+I34),(VLOOKUP(TRIM(D34), CATALOGO!A:B, 2, FALSE) * C34+I34)),"")) -> 53000 | M34: SI
A35: RAPPI | B35: 46025 | C35: 1 | D35: BITES | E35: 2071 | G35: SI | H35: RAPPI | J35: =IF(A35="RAPPI",(VLOOKUP(TRIM(D35), CATALOGO!F:G, 2, FALSE) * C35)+I35,IFERROR(IF(COUNTIF('RESTAURANTESDESCUENTOS 2026'!A:A,TRIM(A35))>0,((VLOOKUP(TRIM(D35), CATALOGO!A:B, 2, FALSE) * C35)*(1-VALUE(SUBSTITUTE(VLOOKUP(TRIM(A35),'RESTAURANTESDESCUENTOS 2026'!A:B,2,FALSE),"%",""))/100)+I35),(VLOOKUP(TRIM(D35), CATALOGO!A:B, 2, FALSE) * C35+I35)),"")) -> #N/A | M35: SI
A36: RAPPI | B36: 46025 | C36: 4 | D36: AREQUIPE | E36: 2071 | G36: SI | H36: RAPPI | J36: 0 | M36: SI
A37: VENTA EN LOCAL | B37: 46025 | C37: 2 | D37: PORCION OG | E37: PAGO EN EFECTIVO | G37: NO | J37: =IF(A37="RAPPI",(VLOOKUP(TRIM(D37), CATALOGO!F:G, 2, FALSE) * C37)+I37,IFERROR(IF(COUNTIF('RESTAURANTESDESCUENTOS 2026'!A:A,TRIM(A37))>0,((VLOOKUP(TRIM(D37), CATALOGO!A:B, 2, FALSE) * C37)*(1-VALUE(SUBSTITUTE(VLOOKUP(TRIM(A37),'RESTAURANTESDESCUENTOS 2026'!A:B,2,FALSE),"%",""))/100)+I37),(VLOOKUP(TRIM(D37), CATALOGO!A:B, 2, FALSE) * C37+I37)),"")) -> 36000 | M37: SI
A38: VENTA EN LOCAL | B38: 46025 | C38: 2 | D38: CARAMELO SALADO | E38: PAGO EN EFECTIVO | G38: NO | J38: 8000 | M38: SI
A39: VENTA EN LOCAL | B39: 46025 | C39: 1 | D39: MEDIANA OG | E39: PAGO EN TRANSFERENCIA | G39: NO | J39: =IF(A39="RAPPI",(VLOOKUP(TRIM(D39), CATALOGO!F:G, 2, FALSE) * C39)+I39,IFERROR(IF(COUNTIF('RESTAURANTESDESCUENTOS 2026'!A:A,TRIM(A39))>0,((VLOOKUP(TRIM(D39), CATALOGO!A:B, 2, FALSE) * C39)*(1-VALUE(SUBSTITUTE(VLOOKUP(TRIM(A39),'RESTAURANTESDESCUENTOS 2026'!A:B,2,FALSE),"%",""))/100)+I39),(VLOOKUP(TRIM(D39), CATALOGO!A:B, 2, FALSE) * C39+I39)),"")) -> 115000 | M39: SI
A40: VENTA EN LOCAL | B40: 46025 | C40: 1 | D40: MEDIANA NAVIDAD | E40: PAGO EN EFECTIVO | G40: NO | J40: =IF(A40="RAPPI",(VLOOKUP(TRIM(D40), CATALOGO!F:G, 2, FALSE) * C40)+I40,IFERROR(IF(COUNTIF('RESTAURANTESDESCUENTOS 2026'!A:A,TRIM(A40))>0,((VLOOKUP(TRIM(D40), CATALOGO!A:B, 2, FALSE) * C40)*(1-VALUE(SUBSTITUTE(VLOOKUP(TRIM(A40),'RESTAURANTESDESCUENTOS 2026'!A:B,2,FALSE),"%",""))/100)+I40),(VLOOKUP(TRIM(D40), CATALOGO!A:B, 2, FALSE) * C40+I40)),"")) -> 123000 | M40: SI
A41: VENTA EN LOCAL | B41: 46025 | C41: 1 | D41: PORCION OG | E41: PAGO EN EFECTIVO | G41: NO | J41: =IF(A41="RAPPI",(VLOOKUP(TRIM(D41), CATALOGO!F:G, 2, FALSE) * C41)+I41,IFERROR(IF(COUNTIF('RESTAURANTESDESCUENTOS 2026'!A:A,TRIM(A41))>0,((VLOOKUP(TRIM(D41), CATALOGO!A:B, 2, FALSE) * C41)*(1-VALUE(SUBSTITUTE(VLOOKUP(TRIM(A41),'RESTAURANTESDESCUENTOS 2026'!A:B,2,FALSE),"%",""))/100)+I41),(VLOOKUP(TRIM(D41), CATALOGO!A:B, 2, FALSE) * C41+I41)),"")) -> 18000 | M41: SI
A42: VENTA EN LOCAL | B42: 46025 | C42: 1 | D42: PORCION OG | E42: PAGO EN TRANSFERENCIA | G42: NO | J42: =IF(A42="RAPPI",(VLOOKUP(TRIM(D42), CATALOGO!F:G, 2, FALSE) * C42)+I42,IFERROR(IF(COUNTIF('RESTAURANTESDESCUENTOS 2026'!A:A,TRIM(A42))>0,((VLOOKUP(TRIM(D42), CATALOGO!A:B, 2, FALSE) * C42)*(1-VALUE(SUBSTITUTE(VLOOKUP(TRIM(A42),'RESTAURANTESDESCUENTOS 2026'!A:B,2,FALSE),"%",""))/100)+I42),(VLOOKUP(TRIM(D42), CATALOGO!A:B, 2, FALSE) * C42+I42)),"")) -> 18000 | M42: SI
A43: VENTA EN LOCAL | B43: 46025 | C43: 1 | D43: CARAMELO SALADO | E43: PAGO EN TRANSFERENCIA | G43: NO | J43: 4000 | M43: SI
A44: RAPPI | B44: 46025 | C44: 2 | D44: PORCION OG + NUTELLA | E44: 5183 | G44: SI | H44: RAPPI | J44: =IF(A44="RAPPI",(VLOOKUP(TRIM(D44), CATALOGO!F:G, 2, FALSE) * C44)+I44,IFERROR(IF(COUNTIF('RESTAURANTESDESCUENTOS 2026'!A:A,TRIM(A44))>0,((VLOOKUP(TRIM(D44), CATALOGO!A:B, 2, FALSE) * C44)*(1-VALUE(SUBSTITUTE(VLOOKUP(TRIM(A44),'RESTAURANTESDESCUENTOS 2026'!A:B,2,FALSE),"%",""))/100)+I44),(VLOOKUP(TRIM(D44), CATALOGO!A:B, 2, FALSE) * C44+I44)),"")) -> 44000 | M44: SI
A45: VENTA EN LOCAL | B45: 46025 | C45: 1 | D45: MEDIANA NAVIDAD | E45: PAGO EN EFECTIVO | G45: NO | J45: =IF(A45="RAPPI",(VLOOKUP(TRIM(D45), CATALOGO!F:G, 2, FALSE) * C45)+I45,IFERROR(IF(COUNTIF('RESTAURANTESDESCUENTOS 2026'!A:A,TRIM(A45))>0,((VLOOKUP(TRIM(D45), CATALOGO!A:B, 2, FALSE) * C45)*(1-VALUE(SUBSTITUTE(VLOOKUP(TRIM(A45),'RESTAURANTESDESCUENTOS 2026'!A:B,2,FALSE),"%",""))/100)+I45),(VLOOKUP(TRIM(D45), CATALOGO!A:B, 2, FALSE) * C45+I45)),"")) -> 123000 | M45: SI
A46: VENTA EN LOCAL | B46: 46025 | C46: 1 | D46: MEDIANA OG + NUTELLA | E46: PAGO EN EFECTIVO | G46: NO | J46: =IF(A46="RAPPI",(VLOOKUP(TRIM(D46), CATALOGO!F:G, 2, FALSE) * C46)+I46,IFERROR(IF(COUNTIF('RESTAURANTESDESCUENTOS 2026'!A:A,TRIM(A46))>0,((VLOOKUP(TRIM(D46), CATALOGO!A:B, 2, FALSE) * C46)*(1-VALUE(SUBSTITUTE(VLOOKUP(TRIM(A46),'RESTAURANTESDESCUENTOS 2026'!A:B,2,FALSE),"%",""))/100)+I46),(VLOOKUP(TRIM(D46), CATALOGO!A:B, 2, FALSE) * C46+I46)),"")) -> 123000 | M46: SI
A47: SE PORCIONA | B47: 46025 | C47: 1 | D47: GRANDE OG | E47: X12 | G47: NO | J47: 0 | M47: SI
A48: RAPPI | B48: 46025 | C48: 1 | D48: MEDIANA NAVIDAD | E48: 3583 | G48: SI | H48: RAPPI | J48: =IF(A48="RAPPI",(VLOOKUP(TRIM(D48), CATALOGO!F:G, 2, FALSE) * C48)+I48,IFERROR(IF(COUNTIF('RESTAURANTESDESCUENTOS 2026'!A:A,TRIM(A48))>0,((VLOOKUP(TRIM(D48), CATALOGO!A:B, 2, FALSE) * C48)*(1-VALUE(SUBSTITUTE(VLOOKUP(TRIM(A48),'RESTAURANTESDESCUENTOS 2026'!A:B,2,FALSE),"%",""))/100)+I48),(VLOOKUP(TRIM(D48), CATALOGO!A:B, 2, FALSE) * C48+I48)),"")) -> 123000 | M48: SI
A49: VENTA EN LOCAL | B49: 46025 | C49: 1 | D49: PORCION OG | E49: PAGO EN EFECTIVO | G49: NO | J49: =IF(A49="RAPPI",(VLOOKUP(TRIM(D49), CATALOGO!F:G, 2, FALSE) * C49)+I49,IFERROR(IF(COUNTIF('RESTAURANTESDESCUENTOS 2026'!A:A,TRIM(A49))>0,((VLOOKUP(TRIM(D49), CATALOGO!A:B, 2, FALSE) * C49)*(1-VALUE(SUBSTITUTE(VLOOKUP(TRIM(A49),'RESTAURANTESDESCUENTOS 2026'!A:B,2,FALSE),"%",""))/100)+I49),(VLOOKUP(TRIM(D49), CATALOGO!A:B, 2, FALSE) * C49+I49)),"")) -> 18000 | M49: SI
A50: HIJO DE TIGRE | B50: 46027 | C50: 1 | D50: GRANDE OG | E50: MARCADA X10 | G50: SI | H50: INDRIVE | I50: 0 | J50: =IF(A50="RAPPI",(VLOOKUP(TRIM(D50), CATALOGO!F:G, 2, FALSE) * C50)+I50,IFERROR(IF(COUNTIF('RESTAURANTESDESCUENTOS 2026'!A:A,TRIM(A50))>0,((VLOOKUP(TRIM(D50), CATALOGO!A:B, 2, FALSE) * C50)*(1-VALUE(SUBSTITUTE(VLOOKUP(TRIM(A50),'RESTAURANTESDESCUENTOS 2026'!A:B,2,FALSE),"%",""))/100)+I50),(VLOOKUP(TRIM(D50), CATALOGO!A:B, 2, FALSE) * C50+I50)),"")) -> 112500 | K50: 10000 | L50: SI | M50: SI
A51: JUANITA ALVAREZ | B51: 46027 | C51: 2 | D51: MEDIANA LOTUS | G51: SI | H51: INDRIVE | I51: 10000 | J51: =IF(A51="RAPPI",(VLOOKUP(TRIM(D51), CATALOGO!F:G, 2, FALSE) * C51)+I51,IFERROR(IF(COUNTIF('RESTAURANTESDESCUENTOS 2026'!A:A,TRIM(A51))>0,((VLOOKUP(TRIM(D51), CATALOGO!A:B, 2, FALSE) * C51)*(1-VALUE(SUBSTITUTE(VLOOKUP(TRIM(A51),'RESTAURANTESDESCUENTOS 2026'!A:B,2,FALSE),"%",""))/100)+I51),(VLOOKUP(TRIM(D51), CATALOGO!A:B, 2, FALSE) * C51+I51)),"")) -> 300000 | K51: 10000 | M51: SI
A52: AMMAZZA INDIANA | B52: 46027 | C52: 2 | D52: MEDIANA OG | E52: INDIANA / MARCADA X10 | G52: SI | H52: INDRIVE | I52: 0 | J52: =IF(A52="RAPPI",(VLOOKUP(TRIM(D52), CATALOGO!F:G, 2, FALSE) * C52)+I52,IFERROR(IF(COUNTIF('RESTAURANTESDESCUENTOS 2026'!A:A,TRIM(A52))>0,((VLOOKUP(TRIM(D52), CATALOGO!A:B, 2, FALSE) * C52)*(1-VALUE(SUBSTITUTE(VLOOKUP(TRIM(A52),'RESTAURANTESDESCUENTOS 2026'!A:B,2,FALSE),"%",""))/100)+I52),(VLOOKUP(TRIM(D52), CATALOGO!A:B, 2, FALSE) * C52+I52)),"")) -> 172500 | K52: 18000 | L52: SI | M52: SI
A53: GENERAL CAFE | B53: 46027 | C53: 1 | D53: GRANDE OG | E53: MARCADA X10 / ORDEN 87 | G53: SI | H53: INDRIVE | I53: 5000 | J53: =IF(A53="RAPPI",(VLOOKUP(TRIM(D53), CATALOGO!F:G, 2, FALSE) * C53)+I53,IFERROR(IF(COUNTIF('RESTAURANTESDESCUENTOS 2026'!A:A,TRIM(A53))>0,((VLOOKUP(TRIM(D53), CATALOGO!A:B, 2, FALSE) * C53)*(1-VALUE(SUBSTITUTE(VLOOKUP(TRIM(A53),'RESTAURANTESDESCUENTOS 2026'!A:B,2,FALSE),"%",""))/100)+I53),(VLOOKUP(TRIM(D53), CATALOGO!A:B, 2, FALSE) * C53+I53)),"")) -> 110000 | K53: 10000 | L53: SI | M53: SI
A54: ENSO | B54: 46027 | C54: 1 | D54: GRANDE OG | E54: MARCADA X10 | G54: SI | H54: INDRIVE | I54: 5000 | J54: =IF(A54="RAPPI",(VLOOKUP(TRIM(D54), CATALOGO!F:G, 2, FALSE) * C54)+I54,IFERROR(IF(COUNTIF('RESTAURANTESDESCUENTOS 2026'!A:A,TRIM(A54))>0,((VLOOKUP(TRIM(D54), CATALOGO!A:B, 2, FALSE) * C54)*(1-VALUE(SUBSTITUTE(VLOOKUP(TRIM(A54),'RESTAURANTESDESCUENTOS 2026'!A:B,2,FALSE),"%",""))/100)+I54),(VLOOKUP(TRIM(D54), CATALOGO!A:B, 2, FALSE) * C54+I54)),"")) -> 110000 | K54: 10000 | L54: SI | M54: SI
A55: SHIBUYA | B55: 46027 | C55: 1 | D55: MEDIANA OG | E55: MARCADA X10 | G55: SI | H55: INDRIVE | I55: 0 | J55: =IF(A55="RAPPI",(VLOOKUP(TRIM(D55), CATALOGO!F:G, 2, FALSE) * C55)+I55,IFERROR(IF(COUNTIF('RESTAURANTESDESCUENTOS 2026'!A:A,TRIM(A55))>0,((VLOOKUP(TRIM(D55), CATALOGO!A:B, 2, FALSE) * C55)*(1-VALUE(SUBSTITUTE(VLOOKUP(TRIM(A55),'RESTAURANTESDESCUENTOS 2026'!A:B,2,FALSE),"%",""))/100)+I55),(VLOOKUP(TRIM(D55), CATALOGO!A:B, 2, FALSE) * C55+I55)),"")) -> 86250 | K55: 0 | L55: SI | M55: SI
A56: AMBIENTE LIVING | B56: 46027 | C56: 1 | D56: GRANDE OG | E56: MARCADA X10 | G56: SI | H56: INDRIVE | I56: 5000 | J56: =IF(A56="RAPPI",(VLOOKUP(TRIM(D56), CATALOGO!F:G, 2, FALSE) * C56)+I56,IFERROR(IF(COUNTIF('RESTAURANTESDESCUENTOS 2026'!A:A,TRIM(A56))>0,((VLOOKUP(TRIM(D56), CATALOGO!A:B, 2, FALSE) * C56)*(1-VALUE(SUBSTITUTE(VLOOKUP(TRIM(A56),'RESTAURANTESDESCUENTOS 2026'!A:B,2,FALSE),"%",""))/100)+I56),(VLOOKUP(TRIM(D56), CATALOGO!A:B, 2, FALSE) * C56+I56)),"")) -> 102125 | K56: 13000 | L56: SI | M56: SI
A57: VICTOR ALZATE | B57: 46027 | C57: 1 | D57: MEDIANA NAVIDAD | G57: NO | J57: =IF(A57="RAPPI",(VLOOKUP(TRIM(D57), CATALOGO!F:G, 2, FALSE) * C57)+I57,IFERROR(IF(COUNTIF('RESTAURANTESDESCUENTOS 2026'!A:A,TRIM(A57))>0,((VLOOKUP(TRIM(D57), CATALOGO!A:B, 2, FALSE) * C57)*(1-VALUE(SUBSTITUTE(VLOOKUP(TRIM(A57),'RESTAURANTESDESCUENTOS 2026'!A:B,2,FALSE),"%",""))/100)+I57),(VLOOKUP(TRIM(D57), CATALOGO!A:B, 2, FALSE) * C57+I57)),"")) -> 123000 | M57: SI
A58: VENTA EN LOCAL | B58: 46027 | C58: 1 | D58: PORCION OG | E58: PAGO EN EFECTIVO | G58: NO | J58: =IF(A58="RAPPI",(VLOOKUP(TRIM(D58), CATALOGO!F:G, 2, FALSE) * C58)+I58,IFERROR(IF(COUNTIF('RESTAURANTESDESCUENTOS 2026'!A:A,TRIM(A58))>0,((VLOOKUP(TRIM(D58), CATALOGO!A:B, 2, FALSE) * C58)*(1-VALUE(SUBSTITUTE(VLOOKUP(TRIM(A58),'RESTAURANTESDESCUENTOS 2026'!A:B,2,FALSE),"%",""))/100)+I58),(VLOOKUP(TRIM(D58), CATALOGO!A:B, 2, FALSE) * C58+I58)),"")) -> 18000 | M58: SI
A59: RAPPI | B59: 46027 | C59: 1 | D59: PORCION OG | E59: 2697 | G59: SI | H59: RAPPI | J59: =IF(A59="RAPPI",(VLOOKUP(TRIM(D59), CATALOGO!F:G, 2, FALSE) * C59)+I59,IFERROR(IF(COUNTIF('RESTAURANTESDESCUENTOS 2026'!A:A,TRIM(A59))>0,((VLOOKUP(TRIM(D59), CATALOGO!A:B, 2, FALSE) * C59)*(1-VALUE(SUBSTITUTE(VLOOKUP(TRIM(A59),'RESTAURANTESDESCUENTOS 2026'!A:B,2,FALSE),"%",""))/100)+I59),(VLOOKUP(TRIM(D59), CATALOGO!A:B, 2, FALSE) * C59+I59)),"")) -> 18000 | M59: SI
A60: RAPPI | B60: 46027 | C60: 2 | D60: PORCION OG + AREQUIPE | E60: 2697 | G60: SI | H60: RAPPI | J60: =IF(A60="RAPPI",(VLOOKUP(TRIM(D60), CATALOGO!F:G, 2, FALSE) * C60)+I60,IFERROR(IF(COUNTIF('RESTAURANTESDESCUENTOS 2026'!A:A,TRIM(A60))>0,((VLOOKUP(TRIM(D60), CATALOGO!A:B, 2, FALSE) * C60)*(1-VALUE(SUBSTITUTE(VLOOKUP(TRIM(A60),'RESTAURANTESDESCUENTOS 2026'!A:B,2,FALSE),"%",""))/100)+I60),(VLOOKUP(TRIM(D60), CATALOGO!A:B, 2, FALSE) * C60+I60)),"")) -> 44000 | M60: SI
A61: RAPPI | B61: 46027 | C61: 1 | D61: MINI OG | E61: 3062 | G61: SI | H61: RAPPI | J61: =IF(A61="RAPPI",(VLOOKUP(TRIM(D61), CATALOGO!F:G, 2, FALSE) * C61)+I61,IFERROR(IF(COUNTIF('RESTAURANTESDESCUENTOS 2026'!A:A,TRIM(A61))>0,((VLOOKUP(TRIM(D61), CATALOGO!A:B, 2, FALSE) * C61)*(1-VALUE(SUBSTITUTE(VLOOKUP(TRIM(A61),'RESTAURANTESDESCUENTOS 2026'!A:B,2,FALSE),"%",""))/100)+I61),(VLOOKUP(TRIM(D61), CATALOGO!A:B, 2, FALSE) * C61+I61)),"")) -> 50000 | M61: SI
A62: RAPPI | B62: 46027 | C62: 1 | D62: GRANDE OG + NUTELLA | E62: 6138 | G62: SI | H62: RAPPI | J62: =IF(A62="RAPPI",(VLOOKUP(TRIM(D62), CATALOGO!F:G, 2, FALSE) * C62)+I62,IFERROR(IF(COUNTIF('RESTAURANTESDESCUENTOS 2026'!A:A,TRIM(A62))>0,((VLOOKUP(TRIM(D62), CATALOGO!A:B, 2, FALSE) * C62)*(1-VALUE(SUBSTITUTE(VLOOKUP(TRIM(A62),'RESTAURANTESDESCUENTOS 2026'!A:B,2,FALSE),"%",""))/100)+I62),(VLOOKUP(TRIM(D62), CATALOGO!A:B, 2, FALSE) * C62+I62)),"")) -> 163000 | M62: SI
A63: RAPPI | B63: 46027 | C63: 1 | D63: MINI OG | E63: 4025 | G63: SI | H63: RAPPI | J63: =IF(A63="RAPPI",(VLOOKUP(TRIM(D63), CATALOGO!F:G, 2, FALSE) * C63)+I63,IFERROR(IF(COUNTIF('RESTAURANTESDESCUENTOS 2026'!A:A,TRIM(A63))>0,((VLOOKUP(TRIM(D63), CATALOGO!A:B, 2, FALSE) * C63)*(1-VALUE(SUBSTITUTE(VLOOKUP(TRIM(A63),'RESTAURANTESDESCUENTOS 2026'!A:B,2,FALSE),"%",""))/100)+I63),(VLOOKUP(TRIM(D63), CATALOGO!A:B, 2, FALSE) * C63+I63)),"")) -> 50000 | M63: SI
A64: RAPPI | B64: 46027 | C64: 1 | D64: GRANDE OG + NUTELLA | E64: 7165 | G64: SI | H64: RAPPI | J64: =IF(A64="RAPPI",(VLOOKUP(TRIM(D64), CATALOGO!F:G, 2, FALSE) * C64)+I64,IFERROR(IF(COUNTIF('RESTAURANTESDESCUENTOS 2026'!A:A,TRIM(A64))>0,((VLOOKUP(TRIM(D64), CATALOGO!A:B, 2, FALSE) * C64)*(1-VALUE(SUBSTITUTE(VLOOKUP(TRIM(A64),'RESTAURANTESDESCUENTOS 2026'!A:B,2,FALSE),"%",""))/100)+I64),(VLOOKUP(TRIM(D64), CATALOGO!A:B, 2, FALSE) * C64+I64)),"")) -> 163000 | M64: SI
A65: VENTA EN LOCAL | B65: 46027 | C65: 1 | D65: MINI OG | E65: PAGO EN EFECTIVO | G65: NO | J65: =IF(A65="RAPPI",(VLOOKUP(TRIM(D65), CATALOGO!F:G, 2, FALSE) * C65)+I65,IFERROR(IF(COUNTIF('RESTAURANTESDESCUENTOS 2026'!A:A,TRIM(A65))>0,((VLOOKUP(TRIM(D65), CATALOGO!A:B, 2, FALSE) * C65)*(1-VALUE(SUBSTITUTE(VLOOKUP(TRIM(A65),'RESTAURANTESDESCUENTOS 2026'!A:B,2,FALSE),"%",""))/100)+I65),(VLOOKUP(TRIM(D65), CATALOGO!A:B, 2, FALSE) * C65+I65)),"")) -> 50000 | M65: SI
A66: VENTA EN LOCAL | B66: 46027 | C66: 1 | D66: MINI OG + AREQUIPE | E66: PAGO EN TRANSFERENCIA | G66: NO | J66: =IF(A66="RAPPI",(VLOOKUP(TRIM(D66), CATALOGO!F:G, 2, FALSE) * C66)+I66,IFERROR(IF(COUNTIF('RESTAURANTESDESCUENTOS 2026'!A:A,TRIM(A66))>0,((VLOOKUP(TRIM(D66), CATALOGO!A:B, 2, FALSE) * C66)*(1-VALUE(SUBSTITUTE(VLOOKUP(TRIM(A66),'RESTAURANTESDESCUENTOS 2026'!A:B,2,FALSE),"%",""))/100)+I66),(VLOOKUP(TRIM(D66), CATALOGO!A:B, 2, FALSE) * C66+I66)),"")) -> 53000 | M66: SI
A67: AMMAZZA AMSTERDAM | B67: 46028 | C67: 1 | D67: MEDIANA OG | E67: AMSTERDAM / MARCADA X10 / SE FACTURA EL 5/1/2026 | G67: SI | H67: DOMICILIARIO JHON | I67: 0 | J67: =IF(A67="RAPPI",(VLOOKUP(TRIM(D67), CATALOGO!F:G, 2, FALSE) * C67)+I67,IFERROR(IF(COUNTIF('RESTAURANTESDESCUENTOS 2026'!A:A,TRIM(A67))>0,((VLOOKUP(TRIM(D67), CATALOGO!A:B, 2, FALSE) * C67)*(1-VALUE(SUBSTITUTE(VLOOKUP(TRIM(A67),'RESTAURANTESDESCUENTOS 2026'!A:B,2,FALSE),"%",""))/100)+I67),(VLOOKUP(TRIM(D67), CATALOGO!A:B, 2, FALSE) * C67+I67)),"")) -> 86250 | K67: 10000 | L67: SI | M67: SI
A68: PDV | B68: 46028 | C68: 6 | D68: GRANDE OG | E68: 3 EN CAJA BLANCA | G68: SI | H68: INDRIVE | I68: 0 | J68: 0 | K68: 220000 | M68: SI
A69: MIGUEL URQUIJO | B69: 46028 | C69: 1 | D69: BITES X4 OG | E69: ENVIAR 1 PM | G69: SI | H69: INDRIVE | I69: 12000 | J69: =IF(A69="RAPPI",(VLOOKUP(TRIM(D69), CATALOGO!F:G, 2, FALSE) * C69)+I69,IFERROR(IF(COUNTIF('RESTAURANTESDESCUENTOS 2026'!A:A,TRIM(A69))>0,((VLOOKUP(TRIM(D69), CATALOGO!A:B, 2, FALSE) * C69)*(1-VALUE(SUBSTITUTE(VLOOKUP(TRIM(A69),'RESTAURANTESDESCUENTOS 2026'!A:B,2,FALSE),"%",""))/100)+I69),(VLOOKUP(TRIM(D69), CATALOGO!A:B, 2, FALSE) * C69+I69)),"")) -> 49000 | K69: 12000 | M69: SI
A70: HIJO DE TIGRE | B70: 46028 | C70: 1 | D70: GRANDE OG | E70: MARCADA X10 | G70: SI | H70: DOMICILIARIO JHON | I70: 10000 | J70: =IF(A70="RAPPI",(VLOOKUP(TRIM(D70), CATALOGO!F:G, 2, FALSE) * C70)+I70,IFERROR(IF(COUNTIF('RESTAURANTESDESCUENTOS 2026'!A:A,TRIM(A70))>0,((VLOOKUP(TRIM(D70), CATALOGO!A:B, 2, FALSE) * C70)*(1-VALUE(SUBSTITUTE(VLOOKUP(TRIM(A70),'RESTAURANTESDESCUENTOS 2026'!A:B,2,FALSE),"%",""))/100)+I70),(VLOOKUP(TRIM(D70), CATALOGO!A:B, 2, FALSE) * C70+I70)),"")) -> 122500 | K70: 10000 | L70: SI | M70: SI
A71: JUDY DUQUE | B71: 46028 | C71: 1 | D71: MINI NAVIDAD | E71: CARAMELO APARTE | G71: SI | H71: DOMICILIARIO JHON | I71: 10000 | J71: =IF(A71="RAPPI",(VLOOKUP(TRIM(D71), CATALOGO!F:G, 2, FALSE) * C71)+I71,IFERROR(IF(COUNTIF('RESTAURANTESDESCUENTOS 2026'!A:A,TRIM(A71))>0,((VLOOKUP(TRIM(D71), CATALOGO!A:B, 2, FALSE) * C71)*(1-VALUE(SUBSTITUTE(VLOOKUP(TRIM(A71),'RESTAURANTESDESCUENTOS 2026'!A:B,2,FALSE),"%",""))/100)+I71),(VLOOKUP(TRIM(D71), CATALOGO!A:B, 2, FALSE) * C71+I71)),"")) -> 63000 | K71: 10000 | M71: SI
A72: ADRIANA JARAMILLO | B72: 46028 | C72: 1 | D72: MINI NAVIDAD | G72: SI | H72: INDRIVE | I72: 26000 | J72: =IF(A72="RAPPI",(VLOOKUP(TRIM(D72), CATALOGO!F:G, 2, FALSE) * C72)+I72,IFERROR(IF(COUNTIF('RESTAURANTESDESCUENTOS 2026'!A:A,TRIM(A72))>0,((VLOOKUP(TRIM(D72), CATALOGO!A:B, 2, FALSE) * C72)*(1-VALUE(SUBSTITUTE(VLOOKUP(TRIM(A72),'RESTAURANTESDESCUENTOS 2026'!A:B,2,FALSE),"%",""))/100)+I72),(VLOOKUP(TRIM(D72), CATALOGO!A:B, 2, FALSE) * C72+I72)),"")) -> 79000 | K72: 26000 | M72: SI
A73: LA FRAGUA | B73: 46028 | C73: 1 | D73: MEDIANA OG | E73: MARCADA X10 | G73: SI | H73: INDRIVE | J73: 78750 | K73: 20000 | L73: SI | M73: SI
A74: VENTA EN LOCAL | B74: 46028 | C74: 1 | D74: PORCION OG | E74: PAGO EN EFECTIVO | G74: NO | J74: =IF(A74="RAPPI",(VLOOKUP(TRIM(D74), CATALOGO!F:G, 2, FALSE) * C74)+I74,IFERROR(IF(COUNTIF('RESTAURANTESDESCUENTOS 2026'!A:A,TRIM(A74))>0,((VLOOKUP(TRIM(D74), CATALOGO!A:B, 2, FALSE) * C74)*(1-VALUE(SUBSTITUTE(VLOOKUP(TRIM(A74),'RESTAURANTESDESCUENTOS 2026'!A:B,2,FALSE),"%",""))/100)+I74),(VLOOKUP(TRIM(D74), CATALOGO!A:B, 2, FALSE) * C74+I74)),"")) -> 18000 | M74: SI
A75: PDV | B75: 46028 | C75: 4 | D75: MEDIANA OG | G75: SI | H75: INDRIVE | I75: 0 | J75: 0 | K75: 0 | M75: SI
A76: PDV | B76: 46028 | C76: 3 | D76: MEDIANA NAVIDAD | G76: SI | H76: INDRIVE | I76: 0 | J76: 0 | K76: 0 | M76: SI
A77: PDV | B77: 46028 | C77: 2 | D77: MINI OG | G77: SI | H77: INDRIVE | I77: 0 | J77: 0 | K77: 0 | M77: SI
A78: PDV | B78: 46028 | C78: 3 | D78: MINI NAVIDAD | G78: SI | H78: INDRIVE | I78: 0 | J78: 0 | K78: 0 | M78: SI
A79: BARBARO RIONEGRO | B79: 46028 | C79: 2 | D79: MEDIANA OG | E79: RIONEGRO / MARCADA X10 | G79: SI | H79: INDRIVE | I79: 0 | J79: =IF(A79="RAPPI",(VLOOKUP(TRIM(D79), CATALOGO!F:G, 2, FALSE) * C79)+I79,IFERROR(IF(COUNTIF('RESTAURANTESDESCUENTOS 2026'!A:A,TRIM(A79))>0,((VLOOKUP(TRIM(D79), CATALOGO!A:B, 2, FALSE) * C79)*(1-VALUE(SUBSTITUTE(VLOOKUP(TRIM(A79),'RESTAURANTESDESCUENTOS 2026'!A:B,2,FALSE),"%",""))/100)+I79),(VLOOKUP(TRIM(D79), CATALOGO!A:B, 2, FALSE) * C79+I79)),"")) -> 172500 | K79: 0 | L79: SI | M79: SI
A80: MIGUEL URQUIJO | B80: 46028 | C80: 1 | D80: CREMA DE MILO | G80: SI | H80: INDRIVE | I80: 0 | J80: =IF(A80="RAPPI",(VLOOKUP(TRIM(D80), CATALOGO!F:G, 2, FALSE) * C80)+I80,IFERROR(IF(COUNTIF('RESTAURANTESDESCUENTOS 2026'!A:A,TRIM(A80))>0,((VLOOKUP(TRIM(D80), CATALOGO!A:B, 2, FALSE) * C80)*(1-VALUE(SUBSTITUTE(VLOOKUP(TRIM(A80),'RESTAURANTESDESCUENTOS 2026'!A:B,2,FALSE),"%",""))/100)+I80),(VLOOKUP(TRIM(D80), CATALOGO!A:B, 2, FALSE) * C80+I80)),"")) -> 0 | K80: 0 | M80: SI
A81: MIGUEL URQUIJO | B81: 46028 | C81: 1 | D81: AREQUIPE | G81: SI | H81: INDRIVE | I81: 0 | J81: =IF(A81="RAPPI",(VLOOKUP(TRIM(D81), CATALOGO!F:G, 2, FALSE) * C81)+I81,IFERROR(IF(COUNTIF('RESTAURANTESDESCUENTOS 2026'!A:A,TRIM(A81))>0,((VLOOKUP(TRIM(D81), CATALOGO!A:B, 2, FALSE) * C81)*(1-VALUE(SUBSTITUTE(VLOOKUP(TRIM(A81),'RESTAURANTESDESCUENTOS 2026'!A:B,2,FALSE),"%",""))/100)+I81),(VLOOKUP(TRIM(D81), CATALOGO!A:B, 2, FALSE) * C81+I81)),"")) -> 0 | K81: 0 | M81: SI
A82: MIGUEL URQUIJO | B82: 46028 | C82: 1 | D82: FRUTOS ROJOS | G82: SI | H82: INDRIVE | I82: 0 | J82: =IF(A82="RAPPI",(VLOOKUP(TRIM(D82), CATALOGO!F:G, 2, FALSE) * C82)+I82,IFERROR(IF(COUNTIF('RESTAURANTESDESCUENTOS 2026'!A:A,TRIM(A82))>0,((VLOOKUP(TRIM(D82), CATALOGO!A:B, 2, FALSE) * C82)*(1-VALUE(SUBSTITUTE(VLOOKUP(TRIM(A82),'RESTAURANTESDESCUENTOS 2026'!A:B,2,FALSE),"%",""))/100)+I82),(VLOOKUP(TRIM(D82), CATALOGO!A:B, 2, FALSE) * C82+I82)),"")) -> 0 | K82: 0 | M82: SI
A83: MIGUEL URQUIJO | B83: 46028 | C83: 1 | D83: CARAMELO SALADO | G83: SI | H83: INDRIVE | I83: 0 | J83: =IF(A83="RAPPI",(VLOOKUP(TRIM(D83), CATALOGO!F:G, 2, FALSE) * C83)+I83,IFERROR(IF(COUNTIF('RESTAURANTESDESCUENTOS 2026'!A:A,TRIM(A83))>0,((VLOOKUP(TRIM(D83), CATALOGO!A:B, 2, FALSE) * C83)*(1-VALUE(SUBSTITUTE(VLOOKUP(TRIM(A83),'RESTAURANTESDESCUENTOS 2026'!A:B,2,FALSE),"%",""))/100)+I83),(VLOOKUP(TRIM(D83), CATALOGO!A:B, 2, FALSE) * C83+I83)),"")) -> 0 | K83: 0 | M83: SI
A84: RAPPI | B84: 46028 | C84: 1 | D84: MINI NAVIDAD | E84: 9417 | G84: SI | H84: RAPPI | J84: =IF(A84="RAPPI",(VLOOKUP(TRIM(D84), CATALOGO!F:G, 2, FALSE) * C84)+I84,IFERROR(IF(COUNTIF('RESTAURANTESDESCUENTOS 2026'!A:A,TRIM(A84))>0,((VLOOKUP(TRIM(D84), CATALOGO!A:B, 2, FALSE) * C84)*(1-VALUE(SUBSTITUTE(VLOOKUP(TRIM(A84),'RESTAURANTESDESCUENTOS 2026'!A:B,2,FALSE),"%",""))/100)+I84),(VLOOKUP(TRIM(D84), CATALOGO!A:B, 2, FALSE) * C84+I84)),"")) -> 53000 | M84: SI
A85: RAPPI | B85: 46028 | C85: 1 | D85: MINI OG + AREQUIPE | E85: 9417 | G85: SI | H85: RAPPI | J85: =IF(A85="RAPPI",(VLOOKUP(TRIM(D85), CATALOGO!F:G, 2, FALSE) * C85)+I85,IFERROR(IF(COUNTIF('RESTAURANTESDESCUENTOS 2026'!A:A,TRIM(A85))>0,((VLOOKUP(TRIM(D85), CATALOGO!A:B, 2, FALSE) * C85)*(1-VALUE(SUBSTITUTE(VLOOKUP(TRIM(A85),'RESTAURANTESDESCUENTOS 2026'!A:B,2,FALSE),"%",""))/100)+I85),(VLOOKUP(TRIM(D85), CATALOGO!A:B, 2, FALSE) * C85+I85)),"")) -> 53000 | M85: SI
A86: RAPPI | B86: 46028 | C86: 1 | D86: MINI OG + FRUTOS ROJOS | E86: 9417 | G86: SI | H86: RAPPI | J86: =IF(A86="RAPPI",(VLOOKUP(TRIM(D86), CATALOGO!F:G, 2, FALSE) * C86)+I86,IFERROR(IF(COUNTIF('RESTAURANTESDESCUENTOS 2026'!A:A,TRIM(A86))>0,((VLOOKUP(TRIM(D86), CATALOGO!A:B, 2, FALSE) * C86)*(1-VALUE(SUBSTITUTE(VLOOKUP(TRIM(A86),'RESTAURANTESDESCUENTOS 2026'!A:B,2,FALSE),"%",""))/100)+I86),(VLOOKUP(TRIM(D86), CATALOGO!A:B, 2, FALSE) * C86+I86)),"")) -> 53000 | M86: SI
A87: RAPPI | B87: 46028 | C87: 1 | D87: MEDIANA OG | E87: 7632 | G87: SI | H87: RAPPI | J87: =IF(A87="RAPPI",(VLOOKUP(TRIM(D87), CATALOGO!F:G, 2, FALSE) * C87)+I87,IFERROR(IF(COUNTIF('RESTAURANTESDESCUENTOS 2026'!A:A,TRIM(A87))>0,((VLOOKUP(TRIM(D87), CATALOGO!A:B, 2, FALSE) * C87)*(1-VALUE(SUBSTITUTE(VLOOKUP(TRIM(A87),'RESTAURANTESDESCUENTOS 2026'!A:B,2,FALSE),"%",""))/100)+I87),(VLOOKUP(TRIM(D87), CATALOGO!A:B, 2, FALSE) * C87+I87)),"")) -> 115000 | M87: SI
A88: ADRIANA JARAMILLO | B88: 46028 | C88: 1 | D88: MINI OG | E88: MENSAJE / REGALO PARA JUAN DIEGO SALAZAR | G88: SI | H88: INDRIVE | I88: 0 | J88: =IF(A88="RAPPI",(VLOOKUP(TRIM(D88), CATALOGO!F:G, 2, FALSE) * C88)+I88,IFERROR(IF(COUNTIF('RESTAURANTESDESCUENTOS 2026'!A:A,TRIM(A88))>0,((VLOOKUP(TRIM(D88), CATALOGO!A:B, 2, FALSE) * C88)*(1-VALUE(SUBSTITUTE(VLOOKUP(TRIM(A88),'RESTAURANTESDESCUENTOS 2026'!A:B,2,FALSE),"%",""))/100)+I88),(VLOOKUP(TRIM(D88), CATALOGO!A:B, 2, FALSE) * C88+I88)),"")) -> 50000 | K88: 0 | M88: SI
A89: VENTA EN LOCAL | B89: 46028 | C89: 1 | D89: MINI OG | E89: PAGO EN EFECTIVO | G89: NO | J89: =IF(A89="RAPPI",(VLOOKUP(TRIM(D89), CATALOGO!F:G, 2, FALSE) * C89)+I89,IFERROR(IF(COUNTIF('RESTAURANTESDESCUENTOS 2026'!A:A,TRIM(A89))>0,((VLOOKUP(TRIM(D89), CATALOGO!A:B, 2, FALSE) * C89)*(1-VALUE(SUBSTITUTE(VLOOKUP(TRIM(A89),'RESTAURANTESDESCUENTOS 2026'!A:B,2,FALSE),"%",""))/100)+I89),(VLOOKUP(TRIM(D89), CATALOGO!A:B, 2, FALSE) * C89+I89)),"")) -> 50000 | M89: SI
A90: MILENA TARTELLE | B90: 46028 | C90: 1 | D90: PORCION OG + AREQUIPE | E90: 30% OFF | G90: NO | J90: 14000 | M90: SI
A91: RAPPI | B91: 46028 | C91: 1 | D91: PORCION OG | E91: 9497 | G91: SI | H91: RAPPI | J91: =IF(A91="RAPPI",(VLOOKUP(TRIM(D91), CATALOGO!F:G, 2, FALSE) * C91)+I91,IFERROR(IF(COUNTIF('RESTAURANTESDESCUENTOS 2026'!A:A,TRIM(A91))>0,((VLOOKUP(TRIM(D91), CATALOGO!A:B, 2, FALSE) * C91)*(1-VALUE(SUBSTITUTE(VLOOKUP(TRIM(A91),'RESTAURANTESDESCUENTOS 2026'!A:B,2,FALSE),"%",""))/100)+I91),(VLOOKUP(TRIM(D91), CATALOGO!A:B, 2, FALSE) * C91+I91)),"")) -> 18000 | M91: SI
A92: RAPPI | B92: 46028 | C92: 1 | D92: MEDIANA NAVIDAD | E92: 4323 | G92: SI | H92: RAPPI | J92: =IF(A92="RAPPI",(VLOOKUP(TRIM(D92), CATALOGO!F:G, 2, FALSE) * C92)+I92,IFERROR(IF(COUNTIF('RESTAURANTESDESCUENTOS 2026'!A:A,TRIM(A92))>0,((VLOOKUP(TRIM(D92), CATALOGO!A:B, 2, FALSE) * C92)*(1-VALUE(SUBSTITUTE(VLOOKUP(TRIM(A92),'RESTAURANTESDESCUENTOS 2026'!A:B,2,FALSE),"%",""))/100)+I92),(VLOOKUP(TRIM(D92), CATALOGO!A:B, 2, FALSE) * C92+I92)),"")) -> 123000 | M92: SI
A93: RAPPI | B93: 46028 | C93: 1 | D93: PORCION OG + AREQUIPE | E93: 604 | G93: SI | H93: RAPPI | J93: =IF(A93="RAPPI",(VLOOKUP(TRIM(D93), CATALOGO!F:G, 2, FALSE) * C93)+I93,IFERROR(IF(COUNTIF('RESTAURANTESDESCUENTOS 2026'!A:A,TRIM(A93))>0,((VLOOKUP(TRIM(D93), CATALOGO!A:B, 2, FALSE) * C93)*(1-VALUE(SUBSTITUTE(VLOOKUP(TRIM(A93),'RESTAURANTESDESCUENTOS 2026'!A:B,2,FALSE),"%",""))/100)+I93),(VLOOKUP(TRIM(D93), CATALOGO!A:B, 2, FALSE) * C93+I93)),"")) -> 22000 | M93: SI
A94: KAREN SARRIA VILLADA | B94: 46029 | C94: 1 | D94: MINI NAVIDAD | E94: MENSAJE | G94: SI | H94: INDRIVE | I94: 14000 | J94: =IF(A94="RAPPI",(VLOOKUP(TRIM(D94), CATALOGO!F:G, 2, FALSE) * C94)+I94,IFERROR(IF(COUNTIF('RESTAURANTESDESCUENTOS 2026'!A:A,TRIM(A94))>0,((VLOOKUP(TRIM(D94), CATALOGO!A:B, 2, FALSE) * C94)*(1-VALUE(SUBSTITUTE(VLOOKUP(TRIM(A94),'RESTAURANTESDESCUENTOS 2026'!A:B,2,FALSE),"%",""))/100)+I94),(VLOOKUP(TRIM(D94), CATALOGO!A:B, 2, FALSE) * C94+I94)),"")) -> 67000 | K94: 14000 | M94: SI
A95: NELSON VARGAS | B95: 46029 | C95: 1 | D95: MINI NAVIDAD | E95: MENSAJE | G95: SI | H95: INDRIVE | I95: 14000 | J95: =IF(A95="RAPPI",(VLOOKUP(TRIM(D95), CATALOGO!F:G, 2, FALSE) * C95)+I95,IFERROR(IF(COUNTIF('RESTAURANTESDESCUENTOS 2026'!A:A,TRIM(A95))>0,((VLOOKUP(TRIM(D95), CATALOGO!A:B, 2, FALSE) * C95)*(1-VALUE(SUBSTITUTE(VLOOKUP(TRIM(A95),'RESTAURANTESDESCUENTOS 2026'!A:B,2,FALSE),"%",""))/100)+I95),(VLOOKUP(TRIM(D95), CATALOGO!A:B, 2, FALSE) * C95+I95)),"")) -> 67000 | K95: 14000 | M95: SI
A96: FANNER SANCHEZ | B96: 46029 | C96: 1 | D96: MEDIANA OG | E96: 25% OFF | G96: SI | H96: INDRIVE | I96: 16000 | J96: 94750 | K96: 16000 | M96: SI
A97: JOSE GUTIERREZ | B97: 46029 | C97: 1 | D97: MINI NAVIDAD | E97: 25% OFF | G97: SI | H97: INDRIVE | I97: 13000 | J97: 50500 | K97: 13000 | M97: SI
A98: BURDO | B98: 46029 | C98: 1 | D98: GRANDE OG | E98: MARCADA X10 | G98: SI | H98: INDRIVE | I98: 5000 | J98: =IF(A98="RAPPI",(VLOOKUP(TRIM(D98), CATALOGO!F:G, 2, FALSE) * C98)+I98,IFERROR(IF(COUNTIF('RESTAURANTESDESCUENTOS 2026'!A:A,TRIM(A98))>0,((VLOOKUP(TRIM(D98), CATALOGO!A:B, 2, FALSE) * C98)*(1-VALUE(SUBSTITUTE(VLOOKUP(TRIM(A98),'RESTAURANTESDESCUENTOS 2026'!A:B,2,FALSE),"%",""))/100)+I98),(VLOOKUP(TRIM(D98), CATALOGO!A:B, 2, FALSE) * C98+I98)),"")) -> 110000 | K98: 10000 | L98: SI | M98: SI
A99: LA ABUELA NITA | B99: 46029 | C99: 1 | D99: GRANDE OG | E99: MARCADA X12 | G99: SI | H99: INDRIVE | I99: 0 | J99: =IF(A99="RAPPI",(VLOOKUP(TRIM(D99), CATALOGO!F:G, 2, FALSE) * C99)+I99,IFERROR(IF(COUNTIF('RESTAURANTESDESCUENTOS 2026'!A:A,TRIM(A99))>0,((VLOOKUP(TRIM(D99), CATALOGO!A:B, 2, FALSE) * C99)*(1-VALUE(SUBSTITUTE(VLOOKUP(TRIM(A99),'RESTAURANTESDESCUENTOS 2026'!A:B,2,FALSE),"%",""))/100)+I99),(VLOOKUP(TRIM(D99), CATALOGO!A:B, 2, FALSE) * C99+I99)),"")) -> 112500 | K99: 0 | L99: SI | M99: SI
A100: ERNESTO SALON COMEDOR | B100: 46029 | C100: 1 | D100: GRANDE OG | E100: MARCADA X10 | G100: SI | H100: INDRIVE | I100: 25000 | J100: =IF(A100="RAPPI",(VLOOKUP(TRIM(D100), CATALOGO!F:G, 2, FALSE) * C100)+I100,IFERROR(IF(COUNTIF('RESTAURANTESDESCUENTOS 2026'!A:A,TRIM(A100))>0,((VLOOKUP(TRIM(D100), CATALOGO!A:B, 2, FALSE) * C100)*(1-VALUE(SUBSTITUTE(VLOOKUP(TRIM(A100),'RESTAURANTESDESCUENTOS 2026'!A:B,2,FALSE),"%",""))/100)+I100),(VLOOKUP(TRIM(D100), CATALOGO!A:B, 2, FALSE) * C100+I100)),"")) -> 137500 | K100: 0 | L100: SI | M100: SI
...

Sheet HOY

Sheet MAÑANA

Sheet CATALOGO
A1: NORMAL | F1: RAPPI | K1: CATALOGO | P1: CATALOGO RESTAURANTES | X1: ACTIVO
A2: PORCION OG | B2: 18000 | F2: PORCION OG | G2: 18000 | K2: PT01 | L2: BITES X4 OG | M2: =VLOOKUP(L2,$A$2:$B$52,2,FALSE) -> 37000 | P2: C16 | Q2: GRANDE ORIGINAL - R | R2: =VLOOKUP(Q2,$A$2:$B$52,2,FALSE) -> #N/A | X2: PENDIENTE
A3: MINI OG | B3: 50000 | F3: MINI OG | G3: 50000 | K3: Dom01 | L3: DOMICILIO | M3: =VLOOKUP(L3,$A$2:$B$52,2,FALSE) -> #N/A | P3: C18 | Q3: MEDIANA ORIGINAL - R | R3: =VLOOKUP(Q3,$A$2:$B$52,2,FALSE) -> #N/A | X3: NO
A4: MEDIANA OG | B4: 115000 | F4: MEDIANA OG | G4: 115000 | K4: PT30 | L4: FRUTOS ROJOS | M4: =VLOOKUP(L4,$A$2:$B$52,2,FALSE) | Q4: VARIEDAD
A5: GRANDE OG | B5: 150000 | F5: GRANDE OG | G5: 150000 | K5: PT59 | L5: GRANDE LIMON | M5: =VLOOKUP(L5,$A$2:$B$52,2,FALSE) -> 154000 | Q5: MINI ORIGINAL - VELEZ CAFE | X5: OK
A6: PORCION OG + AREQUIPE | B6: 22000 | F6: PORCION OG + AREQUIPE | G6: 22000 | K6: PT02 | L6: GRANDE LOTUS | M6: =VLOOKUP(L6,$A$2:$B$52,2,FALSE) -> 189000 | Q6: MINI PISTACHO - VELEZ CAFE
A7: MINI OG + AREQUIPE | B7: 53000 | F7: MINI OG + AREQUIPE | G7: 53000 | K7: PT55 | L7: GRANDE MILO | M7: =VLOOKUP(L7,$A$2:$B$52,2,FALSE) -> 160000 | Q7: MINI MILO - VELEZ CAFE
A8: MEDIANA OG + AREQUIPE | B8: 123000 | F8: MEDIANA OG + AREQUIPE | G8: 123000 | K8: PT13 | L8: GRANDE NUTELLA | M8: =VLOOKUP(L8,$A$2:$B$52,2,FALSE) -> 176000 | Q8: MEDIANA PISTACHO - R
A9: GRANDE OG + AREQUIPE | B9: 163000 | F9: GRANDE OG + AREQUIPE | G9: 163000 | K9: PT19 | L9: GRANDE OG | M9: =VLOOKUP(L9,$A$2:$B$52,2,FALSE) -> 150000
A10: PORCION OG + NUTELLA | B10: 22000 | F10: PORCION OG + NUTELLA | G10: 22000 | K10: C07 | L10: GRANDE OG + AREQUIPE | M10: =VLOOKUP(L10,$A$2:$B$52,2,FALSE) -> 163000
A11: MINI OG + NUTELLA | B11: 53000 | F11: MINI OG + NUTELLA | G11: 53000 | K11: C06 | L11: GRANDE OG + CREMA DE MILO | M11: =VLOOKUP(L11,$A$2:$B$52,2,FALSE) -> 163000
A12: MEDIANA OG + NUTELLA | B12: 123000 | F12: MEDIANA OG + NUTELLA | G12: 123000 | K12: C12 | L12: GRANDE OG + FRUTOS ROJOS | M12: =VLOOKUP(L12,$A$2:$B$52,2,FALSE) -> 163000
A13: GRANDE OG + NUTELLA | B13: 163000 | F13: GRANDE OG + NUTELLA | G13: 163000 | K13: C14 | L13: GRANDE OG + NUTELLA | M13: =VLOOKUP(L13,$A$2:$B$52,2,FALSE) -> 163000
A14: PORCION OG + CREMA DE MILO | B14: 22000 | F14: PORCION OG + CREMA DE MILO | G14: 22000 | K14: C16 | L14: GRANDE ORIGINAL - R | M14: =VLOOKUP(L14,$A$2:$B$52,2,FALSE) -> #N/A
A15: MINI OG + CREMA DE MILO | B15: 53000 | F15: MINI OG + CREMA DE MILO | G15: 53000 | K15: PT22 | L15: GRANDE PISTACHO | M15: =VLOOKUP(L15,$A$2:$B$52,2,FALSE) -> 233000
A16: MEDIANA OG + CREMA DE MILO | B16: 123000 | F16: MEDIANA OG + CREMA DE MILO | G16: 123000 | K16: PT32 | L16: GRANDE VAINILLA | M16: =VLOOKUP(L16,$A$2:$B$52,2,FALSE) -> 163000
A17: GRANDE OG + CREMA DE MILO | B17: 163000 | F17: GRANDE OG + CREMA DE MILO | G17: 163000 | K17: PT58 | L17: MEDIANA LIMON | M17: =VLOOKUP(L17,$A$2:$B$52,2,FALSE) -> 119000
A18: PORCION OG + FRUTOS ROJOS | B18: 22000 | F18: PORCION OG + FRUTOS ROJOS | G18: 22000 | K18: PT23 | L18: MEDIANA LOTUS | M18: =VLOOKUP(L18,$A$2:$B$52,2,FALSE) -> 145000
A19: MINI OG + FRUTOS ROJOS | B19: 53000 | F19: MINI OG + FRUTOS ROJOS | G19: 53000 | K19: PT56 | L19: MEDIANA MILO | M19: =VLOOKUP(L19,$A$2:$B$52,2,FALSE) -> 124000
A20: MEDIANA OG + FRUTOS ROJOS | B20: 123000 | F20: MEDIANA OG + FRUTOS ROJOS | G20: 123000 | K20: PT24 | L20: MEDIANA NUTELLA | M20: =VLOOKUP(L20,$A$2:$B$52,2,FALSE) -> 132000
... A37: PORCION MILO | B37: 22000 | F37: PORCION MILO | G37: 22000 | K37: C08 | L37: MINI OG + NUTELLA | M37: =VLOOKUP(L37,$A$2:$B$52,2,FALSE) -> 53000
A38: MINI LIMON | B38: 55000 | F38: MINI LIMON | G38: 55000
A39: MEDIANA LIMON | B39: 119000 | F39: MEDIANA LIMON | G39: 119000 | K39: PT11 | L39: MINI PISTACHO | M39: =VLOOKUP(L39,$A$2:$B$52,2,FALSE) -> 55000
A40: GRANDE LIMON | B40: 154000 | F40: GRANDE LIMON | G40: 154000 | K40: PT31 | L40: MINI VAINILLA | M40: =VLOOKUP(L40,$A$2:$B$52,2,FALSE) -> 55000
A41: BITES X4 OG | B41: 37000 | F41: BITES X4 OG | G41: 37000 | K41: PT40 | L41: PORCION GRANDE MERMELADA FRUTOS ROJOS | M41: =VLOOKUP(L41,$A$2:$B$52,2,FALSE) -> #N/A
A42: AREQUIPE | F42: AREQUIPE | K42: PT45 | L42: PORCION MEDIANA MERMELADA FRUTOS ROJOS | M42: =VLOOKUP(L42,$A$2:$B$52,2,FALSE) -> #N/A
A43: NUTELLA | F43: NUTELLA | K43: PT52 | L43: PORCION MILO | M43: =VLOOKUP(L43,$A$2:$B$52,2,FALSE) -> 22000
A44: FRUTOS ROJOS | F44: FRUTOS ROJOS | K44: PT42 | L44: PORCION MINI MERMELADA FRUTOS ROJOS | M44: =VLOOKUP(L44,$A$2:$B$52,2,FALSE) -> #N/A
A45: CREMA DE MILO | F45: CREMA DE MILO | K45: PT14 | L45: PORCION OG | M45: =VLOOKUP(L45,$A$2:$B$52,2,FALSE) -> 18000
A46: CARAMELO SALADO | F46: CARAMELO SALADO
A47: VINO | B47: 30000 | K47: C04 | L47: PORCION OG + AREQUIPE | M47: =VLOOKUP(L47,$A$2:$B$52,2,FALSE) -> 22000
A48: VELAS HBD DORADA | B48: 8000 | F48: VELAS HBD DORADA | G48: 8000 | K48: C15 | L48: PORCION OG + CREMA DE MILO | M48: =VLOOKUP(L48,$A$2:$B$52,2,FALSE) -> 22000
A49: VELAS HBD PLATEADA | B49: 8000 | F49: VELAS HBD PLATEADA | G49: 8000 | K49: C10 | L49: PORCION OG + FRUTOS ROJOS | M49: =VLOOKUP(L49,$A$2:$B$52,2,FALSE) -> 22000
A50: VELAS HBD BRONCE | B50: 8000 | F50: VELAS HBD BRONCE | G50: 8000 | K50: C09 | L50: PORCION OG + NUTELLA | M50: =VLOOKUP(L50,$A$2:$B$52,2,FALSE) -> 22000
A51: VELA PALO DORADA | B51: 4000 | F51: VELA PALO DORADA | G51: 4000 | K51: V1 | L51: VELA PALO DORADA | M51: =VLOOKUP(L51,$A$2:$B$52,2,FALSE) -> 4000
A52: VELA PALO PLATEADA | B52: 4000 | F52: VELA PALO PLATEADA | G52: 4000 | K52: V2 | L52: VELA PALO PLATEADA | M52: =VLOOKUP(L52,$A$2:$B$52,2,FALSE) -> 4000
A53: MINI NAVIDAD | B53: 53000 | F53: MINI NAVIDAD | G53: 53000 | K53: V5 | L53: VELAS HBD BRONCE | M53: =VLOOKUP(L53,$A$2:$B$52,2,FALSE) -> 8000
A54: MEDIANA NAVIDAD | B54: 123000 | F54: MEDIANA NAVIDAD | G54: 123000 | K54: V3 | L54: VELAS HBD DORADA | M54: =VLOOKUP(L54,$A$2:$B$52,2,FALSE) -> 8000
A55: GRANDE NAVIDAD | B55: 163000 | F55: GRANDE NAVIDAD | G55: 163000 | K55: V4 | L55: VELAS HBD PLATEADA | M55: =VLOOKUP(L55,$A$2:$B$52,2,FALSE) -> 8000
A56: BITES X4 LOTUS | B56: 37000 | F56: BITES X4 LOTUS | G56: 37000
A57: BITES X4 NUTELLA | B57: 37000 | F57: BITES X4 NUTELLA | G57: 37000
A58: BITES X4 LIMON | B58: 37000 | F58: BITES X4 LIMON | G58: 37000
A59: BITES X4 PISTACHO | B59: 37000 | F59: BITES X4 PISTACHO | G59: 37000
A60: BITES X4 VAINILLA MADAGASCAR | B60: 37000 | F60: BITES X4 VAINILLA MADAGASCAR | G60: 37000
A61: BITES X4 MILO | B61: 37000 | F61: BITES X4 MILO | G61: 37000
A62: BITES X4 OG | B62: 37000
A63: GALLETA CHIPS CHOCOLATE X35 | B63: 105000 | F63: GALLETA CHIPS CHOCOLATE X35 | G63: 105000
A64: GALLETA CHIPS CHOCOLATE BLANCO X35 | B64: 105000 | F64: GALLETA CHIPS CHOCOLATE BLANCO X35 | G64: 105000
A65: MASA GALLETA DE BITES | F65: MASA GALLETA DE BITES
A66: GRANDE ORIGINAL X COOKIE WORLD | B66: 182000 | F66: GRANDE ORIGINAL X COOKIE WORLD | G66: 182000
A67: MEDIANA ORIGINAL X COOKIE WORLD | B67: 149000 | F67: MEDIANA ORIGINAL X COOKIE WORLD | G67: 149000
A68: MINI ORIGINAL X COOKIE WORLD | B68: 55000 | F68: MINI ORIGINAL X COOKIE WORLD | G68: 55000
A69: MINI ORIGINAL VELEZ CAFE | B69: 15400
A70: MINI PISTACHO VELEZ CAFE | B70: 24000
A71: MINI MILO CAFE VELEZ CAFE | B71: 17600
A72: BITE X16 ORIGINAL VELEZ CAFE | B72: 64000
A73: BITE X16 MILO VELEZ CAFE | B73: 64000
A74: BITE X16 PISTACHO VELEZ CAFE | B74: 64000
A75: BROWNIES DOBLE CHOCOLATE + FRAMBUESA X41U | B75: 164000
A76: BROWNIES MILO + FRAMBUESA X41 U | B76: 164000
A77: DUO SUCREE X16U | B77: 96000
A78: GALLETA CHIPS CHOCOLATE X35U | B78: 105000
A79: GALLETA CHIPS BLANCO X35U | B79: 105000
A80: MINI TARTA ORIGINAL CAPACILLO X12 | B80: 72000
... A90: BITE X16 ORIGINAL | B90: 64000
